{
"meta":{"test_sets":[],"test_metrics":[],"learn_metrics":[{"best_value":"Min","name":"RMSE"}],"launch_mode":"Train","parameters":"","iteration_count":1000,"learn_sets":["learn"],"name":"experiment"},
"iterations":[
{"learn":[3.912314542],"iteration":0,"passed_time":0.004824039589,"remaining_time":4.819215549},
{"learn":[3.890899981],"iteration":1,"passed_time":0.01033170845,"remaining_time":5.155522518},
{"learn":[3.872156785],"iteration":2,"passed_time":0.01458711764,"remaining_time":4.84778543},
{"learn":[3.852060962],"iteration":3,"passed_time":0.01716786772,"remaining_time":4.274799063},
{"learn":[3.833465364],"iteration":4,"passed_time":0.01970819932,"remaining_time":3.921931665},
{"learn":[3.814790882],"iteration":5,"passed_time":0.03369061698,"remaining_time":5.581412214},
{"learn":[3.794693495],"iteration":6,"passed_time":0.03897942462,"remaining_time":5.529509806},
{"learn":[3.777389652],"iteration":7,"passed_time":0.0405912705,"remaining_time":5.033317542},
{"learn":[3.759455767],"iteration":8,"passed_time":0.04196784322,"remaining_time":4.621125847},
{"learn":[3.739085129],"iteration":9,"passed_time":0.04327916968,"remaining_time":4.284637798},
{"learn":[3.725145422],"iteration":10,"passed_time":0.04378848453,"remaining_time":3.936982836},
{"learn":[3.700241947],"iteration":11,"passed_time":0.04519713805,"remaining_time":3.721231032},
{"learn":[3.678030053],"iteration":12,"passed_time":0.04668981711,"remaining_time":3.544834576},
{"learn":[3.661680583],"iteration":13,"passed_time":0.04822864442,"remaining_time":3.396674528},
{"learn":[3.637757012],"iteration":14,"passed_time":0.04961788977,"remaining_time":3.258241428},
{"learn":[3.618675958],"iteration":15,"passed_time":0.05108559224,"remaining_time":3.141763923},
{"learn":[3.603060175],"iteration":16,"passed_time":0.05287862298,"remaining_time":3.057628611},
{"learn":[3.58745852],"iteration":17,"passed_time":0.05406097165,"remaining_time":2.949326342},
{"learn":[3.572889984],"iteration":18,"passed_time":0.05555187012,"remaining_time":2.868230768},
{"learn":[3.556085213],"iteration":19,"passed_time":0.05674753493,"remaining_time":2.780629211},
{"learn":[3.543267685],"iteration":20,"passed_time":0.05761226519,"remaining_time":2.685828934},
{"learn":[3.523297286],"iteration":21,"passed_time":0.0591913625,"remaining_time":2.631325115},
{"learn":[3.509551041],"iteration":22,"passed_time":0.06075922264,"remaining_time":2.580946109},
{"learn":[3.49396296],"iteration":23,"passed_time":0.06240122489,"remaining_time":2.537649812},
{"learn":[3.479660547],"iteration":24,"passed_time":0.06390765303,"remaining_time":2.492398468},
{"learn":[3.462733372],"iteration":25,"passed_time":0.06554618224,"remaining_time":2.455460827},
{"learn":[3.447031902],"iteration":26,"passed_time":0.06737580044,"remaining_time":2.428024216},
{"learn":[3.427970905],"iteration":27,"passed_time":0.06913277552,"remaining_time":2.399894922},
{"learn":[3.410824104],"iteration":28,"passed_time":0.0709891966,"remaining_time":2.376914135},
{"learn":[3.392125924],"iteration":29,"passed_time":0.07275188681,"remaining_time":2.352311007},
{"learn":[3.371739091],"iteration":30,"passed_time":0.07453391452,"remaining_time":2.329785909},
{"learn":[3.357913927],"iteration":31,"passed_time":0.07645826971,"remaining_time":2.312862659},
{"learn":[3.340932254],"iteration":32,"passed_time":0.07848628203,"remaining_time":2.299885901},
{"learn":[3.323590452],"iteration":33,"passed_time":0.0801061408,"remaining_time":2.275956824},
{"learn":[3.308608495],"iteration":34,"passed_time":0.08333717662,"remaining_time":2.297725012},
{"learn":[3.292243973],"iteration":35,"passed_time":0.09319661701,"remaining_time":2.4955983},
{"learn":[3.278485309],"iteration":36,"passed_time":0.09693602045,"remaining_time":2.522956424},
{"learn":[3.260651635],"iteration":37,"passed_time":0.1007288705,"remaining_time":2.550030879},
{"learn":[3.244049712],"iteration":38,"passed_time":0.102186727,"remaining_time":2.51798576},
{"learn":[3.226491029],"iteration":39,"passed_time":0.1037492332,"remaining_time":2.489981597},
{"learn":[3.213473575],"iteration":40,"passed_time":0.1053021251,"remaining_time":2.463042389},
{"learn":[3.202159155],"iteration":41,"passed_time":0.1063796688,"remaining_time":2.426469588},
{"learn":[3.18649823],"iteration":42,"passed_time":0.1077986701,"remaining_time":2.399147146},
{"learn":[3.168577354],"iteration":43,"passed_time":0.1089485214,"remaining_time":2.367154238},
{"learn":[3.155945345],"iteration":44,"passed_time":0.1100493946,"remaining_time":2.335492709},
{"learn":[3.138158079],"iteration":45,"passed_time":0.1111189633,"remaining_time":2.304510674},
{"learn":[3.117906276],"iteration":46,"passed_time":0.1125114647,"remaining_time":2.281349487},
{"learn":[3.10123306],"iteration":47,"passed_time":0.1144758965,"remaining_time":2.270438613},
{"learn":[3.089839593],"iteration":48,"passed_time":0.1155441218,"remaining_time":2.242499179},
{"learn":[3.077297418],"iteration":49,"passed_time":0.1169400784,"remaining_time":2.221861489},
{"learn":[3.064252081],"iteration":50,"passed_time":0.1181289013,"remaining_time":2.198124065},
{"learn":[3.047480966],"iteration":51,"passed_time":0.1193249148,"remaining_time":2.175384985},
{"learn":[3.033311708],"iteration":52,"passed_time":0.1205510576,"remaining_time":2.153997198},
{"learn":[3.020523007],"iteration":53,"passed_time":0.1218601776,"remaining_time":2.134809779},
{"learn":[3.005363014],"iteration":54,"passed_time":0.1232033854,"remaining_time":2.116858167},
{"learn":[2.991673189],"iteration":55,"passed_time":0.124887424,"remaining_time":2.105245147},
{"learn":[2.97586441],"iteration":56,"passed_time":0.1264270393,"remaining_time":2.091591195},
{"learn":[2.963546799],"iteration":57,"passed_time":0.1287517301,"remaining_time":2.091105685},
{"learn":[2.950744067],"iteration":58,"passed_time":0.1298383114,"remaining_time":2.070811034},
{"learn":[2.939164519],"iteration":59,"passed_time":0.1311698419,"remaining_time":2.05499419},
{"learn":[2.93023724],"iteration":60,"passed_time":0.1315230545,"remaining_time":2.024592593},
{"learn":[2.918923721],"iteration":61,"passed_time":0.1327436102,"remaining_time":2.008282361},
{"learn":[2.904493088],"iteration":62,"passed_time":0.1340250962,"remaining_time":1.993357383},
{"learn":[2.892861402],"iteration":63,"passed_time":0.1353899488,"remaining_time":1.980078002},
{"learn":[2.879076748],"iteration":64,"passed_time":0.1366960109,"remaining_time":1.966319542},
{"learn":[2.870189795],"iteration":65,"passed_time":0.1380786618,"remaining_time":1.954022274},
{"learn":[2.855969054],"iteration":66,"passed_time":0.1392831718,"remaining_time":1.939570138},
{"learn":[2.846068999],"iteration":67,"passed_time":0.1401879457,"remaining_time":1.921399492},
{"learn":[2.835186962],"iteration":68,"passed_time":0.1413502121,"remaining_time":1.907203586},
{"learn":[2.820204231],"iteration":69,"passed_time":0.1431767616,"remaining_time":1.902205547},
{"learn":[2.806646759],"iteration":70,"passed_time":0.1446065464,"remaining_time":1.892105375},
{"learn":[2.792538655],"iteration":71,"passed_time":0.1459476263,"remaining_time":1.881102739},
{"learn":[2.783940501],"iteration":72,"passed_time":0.1466705898,"remaining_time":1.862515571},
{"learn":[2.76904195],"iteration":73,"passed_time":0.1478752193,"remaining_time":1.850438555},
{"learn":[2.757885293],"iteration":74,"passed_time":0.1489668462,"remaining_time":1.83725777},
{"learn":[2.744638912],"iteration":75,"passed_time":0.1500479001,"remaining_time":1.824266575},
{"learn":[2.735995207],"iteration":76,"passed_time":0.1511891993,"remaining_time":1.812306895},
{"learn":[2.725751657],"iteration":77,"passed_time":0.1520628918,"remaining_time":1.797461362},
{"learn":[2.712264046],"iteration":78,"passed_time":0.1532992688,"remaining_time":1.787197805},
{"learn":[2.701820478],"iteration":79,"passed_time":0.1544339931,"remaining_time":1.77599092},
{"learn":[2.690033036],"iteration":80,"passed_time":0.1556438941,"remaining_time":1.765885663},
{"learn":[2.676343112],"iteration":81,"passed_time":0.1567515346,"remaining_time":1.754852546},
{"learn":[2.667900276],"iteration":82,"passed_time":0.1585524362,"remaining_time":1.75171788},
{"learn":[2.652121122],"iteration":83,"passed_time":0.1598865886,"remaining_time":1.74352518},
{"learn":[2.641538583],"iteration":84,"passed_time":0.160930475,"remaining_time":1.732369231},
{"learn":[2.628358152],"iteration":85,"passed_time":0.1620211397,"remaining_time":1.721945601},
{"learn":[2.615987365],"iteration":86,"passed_time":0.1631696191,"remaining_time":1.712343244},
{"learn":[2.601070986],"iteration":87,"passed_time":0.1642498575,"remaining_time":1.702225795},
{"learn":[2.587698927],"iteration":88,"passed_time":0.1654743852,"remaining_time":1.69378837},
{"learn":[2.573663297],"iteration":89,"passed_time":0.1665619148,"remaining_time":1.684126027},
{"learn":[2.563426957],"iteration":90,"passed_time":0.1677033835,"remaining_time":1.675190941},
{"learn":[2.553006631],"iteration":91,"passed_time":0.1688211198,"remaining_time":1.666191052},
{"learn":[2.542537246],"iteration":92,"passed_time":0.1699536384,"remaining_time":1.657504839},
{"learn":[2.531914636],"iteration":93,"passed_time":0.1710368733,"remaining_time":1.648504332},
{"learn":[2.519730967],"iteration":94,"passed_time":0.1726306184,"remaining_time":1.644533786},
{"learn":[2.51209673],"iteration":95,"passed_time":0.1732648006,"remaining_time":1.631576872},
{"learn":[2.497400985],"iteration":96,"passed_time":0.1745613693,"remaining_time":1.625040376},
{"learn":[2.487772249],"iteration":97,"passed_time":0.1756353815,"remaining_time":1.616562389},
{"learn":[2.471002833],"iteration":98,"passed_time":0.1767107363,"remaining_time":1.608246196},
{"learn":[2.463446041],"iteration":99,"passed_time":0.1774947827,"remaining_time":1.597453045},
{"learn":[2.452226302],"iteration":100,"passed_time":0.1785730267,"remaining_time":1.589476743},
{"learn":[2.438236282],"iteration":101,"passed_time":0.1798105644,"remaining_time":1.583038106},
{"learn":[2.427749157],"iteration":102,"passed_time":0.1812446617,"remaining_time":1.578412248},
{"learn":[2.413711523],"iteration":103,"passed_time":0.1824458917,"remaining_time":1.571841529},
{"learn":[2.406695025],"iteration":104,"passed_time":0.1833689703,"remaining_time":1.563002176},
{"learn":[2.393909435],"iteration":105,"passed_time":0.1847087354,"remaining_time":1.557826504},
{"learn":[2.382727362],"iteration":106,"passed_time":0.1860018208,"remaining_time":1.552332953},
{"learn":[2.373752946],"iteration":107,"passed_time":0.1885254624,"remaining_time":1.557080671},
{"learn":[2.364664252],"iteration":108,"passed_time":0.1894838261,"remaining_time":1.5488999},
{"learn":[2.351131091],"iteration":109,"passed_time":0.1908769532,"remaining_time":1.544368076},
{"learn":[2.341378978],"iteration":110,"passed_time":0.1921090702,"remaining_time":1.538603274},
{"learn":[2.33162264],"iteration":111,"passed_time":0.1935214919,"remaining_time":1.534348971},
{"learn":[2.3201256],"iteration":112,"passed_time":0.1950890223,"remaining_time":1.531362502},
{"learn":[2.310199845],"iteration":113,"passed_time":0.1967007407,"remaining_time":1.528744353},
{"learn":[2.300497942],"iteration":114,"passed_time":0.1976905142,"remaining_time":1.521357436},
{"learn":[2.290275055],"iteration":115,"passed_time":0.1986269939,"remaining_time":1.513674678},
{"learn":[2.283802324],"iteration":116,"passed_time":0.1992042543,"remaining_time":1.50339621},
{"learn":[2.274670182],"iteration":117,"passed_time":0.2003032459,"remaining_time":1.497181889},
{"learn":[2.266363992],"iteration":118,"passed_time":0.2019010129,"remaining_time":1.494746155},
{"learn":[2.256750478],"iteration":119,"passed_time":0.2034740536,"remaining_time":1.49214306},
{"learn":[2.247948033],"iteration":120,"passed_time":0.2047599209,"remaining_time":1.48747083},
{"learn":[2.239907881],"iteration":121,"passed_time":0.205914099,"remaining_time":1.481906385},
{"learn":[2.228427381],"iteration":122,"passed_time":0.2071886878,"remaining_time":1.477272188},
{"learn":[2.218636597],"iteration":123,"passed_time":0.2084994321,"remaining_time":1.472947601},
{"learn":[2.206579366],"iteration":124,"passed_time":0.2100018672,"remaining_time":1.47001307},
{"learn":[2.195978222],"iteration":125,"passed_time":0.2111571824,"remaining_time":1.464693472},
{"learn":[2.188497905],"iteration":126,"passed_time":0.2121085857,"remaining_time":1.458037759},
{"learn":[2.181594098],"iteration":127,"passed_time":0.2134022639,"remaining_time":1.453802923},
{"learn":[2.174891134],"iteration":128,"passed_time":0.214494378,"remaining_time":1.448252738},
{"learn":[2.165165317],"iteration":129,"passed_time":0.2162592096,"remaining_time":1.447273172},
{"learn":[2.15573049],"iteration":130,"passed_time":0.2178527402,"remaining_time":1.445145277},
{"learn":[2.142101064],"iteration":131,"passed_time":0.2192602238,"remaining_time":1.441802078},
{"learn":[2.131400747],"iteration":132,"passed_time":0.2204409667,"remaining_time":1.437009911},
{"learn":[2.125357666],"iteration":133,"passed_time":0.2217313482,"remaining_time":1.432980205},
{"learn":[2.114377477],"iteration":134,"passed_time":0.2228944104,"remaining_time":1.428175296},
{"learn":[2.10822357],"iteration":135,"passed_time":0.2236763436,"remaining_time":1.421002653},
{"learn":[2.101431002],"iteration":136,"passed_time":0.2252872733,"remaining_time":1.419145378},
{"learn":[2.094932181],"iteration":137,"passed_time":0.2262893408,"remaining_time":1.413488491},
{"learn":[2.084776692],"iteration":138,"passed_time":0.2273884173,"remaining_time":1.408499477},
{"learn":[2.078799212],"iteration":139,"passed_time":0.2285487924,"remaining_time":1.403942582},
{"learn":[2.070232621],"iteration":140,"passed_time":0.2297113539,"remaining_time":1.399447184},
{"learn":[2.057264913],"iteration":141,"passed_time":0.2314224463,"remaining_time":1.398313091},
{"learn":[2.052845704],"iteration":142,"passed_time":0.2318234935,"remaining_time":1.389319817},
{"learn":[2.042744148],"iteration":143,"passed_time":0.2334474666,"remaining_time":1.387715496},
{"learn":[2.034713415],"iteration":144,"passed_time":0.2348006249,"remaining_time":1.38451403},
{"learn":[2.027847606],"iteration":145,"passed_time":0.2359917246,"remaining_time":1.380389951},
{"learn":[2.020405897],"iteration":146,"passed_time":0.2371557693,"remaining_time":1.376148784},
{"learn":[2.007661199],"iteration":147,"passed_time":0.2383442511,"remaining_time":1.372089878},
{"learn":[2.001900096],"iteration":148,"passed_time":0.2397710854,"remaining_time":1.36943083},
{"learn":[1.994170899],"iteration":149,"passed_time":0.2409773156,"remaining_time":1.365538122},
{"learn":[1.985266558],"iteration":150,"passed_time":0.2419120415,"remaining_time":1.360154458},
{"learn":[1.974904819],"iteration":151,"passed_time":0.2429306755,"remaining_time":1.355297453},
{"learn":[1.969672384],"iteration":152,"passed_time":0.2442127414,"remaining_time":1.351948967},
{"learn":[1.959890845],"iteration":153,"passed_time":0.2457474436,"remaining_time":1.350015177},
{"learn":[1.951537951],"iteration":154,"passed_time":0.2471614575,"remaining_time":1.347428591},
{"learn":[1.945712892],"iteration":155,"passed_time":0.2483845273,"remaining_time":1.343823981},
{"learn":[1.934958195],"iteration":156,"passed_time":0.2496498939,"remaining_time":1.340476819},
{"learn":[1.929289828],"iteration":157,"passed_time":0.2507015734,"remaining_time":1.336017246},
{"learn":[1.922428227],"iteration":158,"passed_time":0.2519599473,"remaining_time":1.332693809},
{"learn":[1.917639347],"iteration":159,"passed_time":0.2527680377,"remaining_time":1.327032198},
{"learn":[1.912248137],"iteration":160,"passed_time":0.2540105167,"remaining_time":1.323694556},
{"learn":[1.902838784],"iteration":161,"passed_time":0.2554024681,"remaining_time":1.321155977},
{"learn":[1.897434385],"iteration":162,"passed_time":0.2565790881,"remaining_time":1.317525747},
{"learn":[1.887554277],"iteration":163,"passed_time":0.257608223,"remaining_time":1.313173624},
{"learn":[1.879361269],"iteration":164,"passed_time":0.2587318243,"remaining_time":1.309339838},
{"learn":[1.871279594],"iteration":165,"passed_time":0.2600683518,"remaining_time":1.306608466},
{"learn":[1.863091146],"iteration":166,"passed_time":0.2617173216,"remaining_time":1.305452269},
{"learn":[1.857162974],"iteration":167,"passed_time":0.2627241616,"remaining_time":1.301110134},
{"learn":[1.850131539],"iteration":168,"passed_time":0.2639125724,"remaining_time":1.297700282},
{"learn":[1.843229284],"iteration":169,"passed_time":0.2650989962,"remaining_time":1.294306864},
{"learn":[1.833308922],"iteration":170,"passed_time":0.2665246223,"remaining_time":1.2920989},
{"learn":[1.823965549],"iteration":171,"passed_time":0.2679840628,"remaining_time":1.290062814},
{"learn":[1.816483717],"iteration":172,"passed_time":0.2688781846,"remaining_time":1.285330975},
{"learn":[1.809279764],"iteration":173,"passed_time":0.2701145652,"remaining_time":1.282267993},
{"learn":[1.800121638],"iteration":174,"passed_time":0.2712493062,"remaining_time":1.278746729},
{"learn":[1.787610993],"iteration":175,"passed_time":0.2724913994,"remaining_time":1.275755188},
{"learn":[1.778812992],"iteration":176,"passed_time":0.2736184188,"remaining_time":1.272248354},
{"learn":[1.772517225],"iteration":177,"passed_time":0.2747393951,"remaining_time":1.268740353},
{"learn":[1.766159173],"iteration":178,"passed_time":0.2763260331,"remaining_time":1.267394822},
{"learn":[1.754867177],"iteration":179,"passed_time":0.2778982839,"remaining_time":1.265981071},
{"learn":[1.748714268],"iteration":180,"passed_time":0.2790704186,"remaining_time":1.262755099},
{"learn":[1.738649971],"iteration":181,"passed_time":0.2803325357,"remaining_time":1.259956122},
{"learn":[1.728798457],"iteration":182,"passed_time":0.2814773647,"remaining_time":1.256650311},
{"learn":[1.71864336],"iteration":183,"passed_time":0.2825096853,"remaining_time":1.252869039},
{"learn":[1.714789377],"iteration":184,"passed_time":0.2830124205,"remaining_time":1.246784447},
{"learn":[1.709688518],"iteration":185,"passed_time":0.2841295865,"remaining_time":1.243448836},
{"learn":[1.702083528],"iteration":186,"passed_time":0.2852241867,"remaining_time":1.240038844},
{"learn":[1.692721843],"iteration":187,"passed_time":0.2862699534,"remaining_time":1.236442565},
{"learn":[1.681149207],"iteration":188,"passed_time":0.2875529444,"remaining_time":1.233891206},
{"learn":[1.676597344],"iteration":189,"passed_time":0.2884356063,"remaining_time":1.229646532},
{"learn":[1.670069996],"iteration":190,"passed_time":0.2896207057,"remaining_time":1.226718067},
{"learn":[1.666449433],"iteration":191,"passed_time":0.2907386443,"remaining_time":1.223525128},
{"learn":[1.659250206],"iteration":192,"passed_time":0.2919699308,"remaining_time":1.220827638},
{"learn":[1.646524243],"iteration":193,"passed_time":0.2930938126,"remaining_time":1.217699036},
{"learn":[1.640163418],"iteration":194,"passed_time":0.2942199801,"remaining_time":1.214600431},
{"learn":[1.6325319],"iteration":195,"passed_time":0.2955569252,"remaining_time":1.212386571},
{"learn":[1.628193346],"iteration":196,"passed_time":0.2966224312,"remaining_time":1.209075189},
{"learn":[1.621054158],"iteration":197,"passed_time":0.2977522252,"remaining_time":1.206046892},
{"learn":[1.613855941],"iteration":198,"passed_time":0.2989608336,"remaining_time":1.203354913},
{"learn":[1.605120678],"iteration":199,"passed_time":0.3000857015,"remaining_time":1.200342806},
{"learn":[1.598987332],"iteration":200,"passed_time":0.3015117924,"remaining_time":1.198546876},
{"learn":[1.591504587],"iteration":201,"passed_time":0.3026997545,"remaining_time":1.195813881},
{"learn":[1.587408901],"iteration":202,"passed_time":0.3035233257,"remaining_time":1.191665471},
{"learn":[1.576681854],"iteration":203,"passed_time":0.3048879945,"remaining_time":1.189660998},
{"learn":[1.571913566],"iteration":204,"passed_time":0.3061537602,"remaining_time":1.187279216},
{"learn":[1.568050557],"iteration":205,"passed_time":0.3074225385,"remaining_time":1.184919882},
{"learn":[1.564047314],"iteration":206,"passed_time":0.3080962162,"remaining_time":1.180291302},
{"learn":[1.556787521],"iteration":207,"passed_time":0.3092333971,"remaining_time":1.177465627},
{"learn":[1.551951334],"iteration":208,"passed_time":0.3098616235,"remaining_time":1.172729877},
{"learn":[1.54317693],"iteration":209,"passed_time":0.3109336666,"remaining_time":1.169702841},
{"learn":[1.53648075],"iteration":210,"passed_time":0.3119278508,"remaining_time":1.166403196},
{"learn":[1.525146445],"iteration":211,"passed_time":0.3129723287,"remaining_time":1.163312241},
{"learn":[1.517570105],"iteration":212,"passed_time":0.3141077307,"remaining_time":1.160576451},
{"learn":[1.511248644],"iteration":213,"passed_time":0.315151201,"remaining_time":1.157517963},
{"learn":[1.503164227],"iteration":214,"passed_time":0.3161900305,"remaining_time":1.154461274},
{"learn":[1.495214983],"iteration":215,"passed_time":0.3173009267,"remaining_time":1.151684845},
{"learn":[1.483936589],"iteration":216,"passed_time":0.3184265659,"remaining_time":1.148976964},
{"learn":[1.479472704],"iteration":217,"passed_time":0.3198604794,"remaining_time":1.147389426},
{"learn":[1.471441577],"iteration":218,"passed_time":0.3211548811,"remaining_time":1.145305763},
{"learn":[1.467418265],"iteration":219,"passed_time":0.3219519935,"remaining_time":1.141466159},
{"learn":[1.458522128],"iteration":220,"passed_time":0.3230141292,"remaining_time":1.138588265},
{"learn":[1.45090914],"iteration":221,"passed_time":0.3240964433,"remaining_time":1.135797446},
{"learn":[1.439996258],"iteration":222,"passed_time":0.3253658727,"remaining_time":1.133673915},
{"learn":[1.434666557],"iteration":223,"passed_time":0.3263083609,"remaining_time":1.130425393},
{"learn":[1.43062462],"iteration":224,"passed_time":0.327406174,"remaining_time":1.127732377},
{"learn":[1.426711601],"iteration":225,"passed_time":0.328352722,"remaining_time":1.124535428},
{"learn":[1.421673861],"iteration":226,"passed_time":0.3294110934,"remaining_time":1.121739098},
{"learn":[1.415354613],"iteration":227,"passed_time":0.3304820159,"remaining_time":1.11900051},
{"learn":[1.409004023],"iteration":228,"passed_time":0.3315582786,"remaining_time":1.116294467},
{"learn":[1.403540812],"iteration":229,"passed_time":0.3326272895,"remaining_time":1.113578317},
{"learn":[1.395926426],"iteration":230,"passed_time":0.3337529134,"remaining_time":1.111064893},
{"learn":[1.388005481],"iteration":231,"passed_time":0.3355645353,"remaining_time":1.110834324},
{"learn":[1.382138394],"iteration":232,"passed_time":0.3367545457,"remaining_time":1.108543934},
{"learn":[1.374972953],"iteration":233,"passed_time":0.3379264984,"remaining_time":1.106203837},
{"learn":[1.368942544],"iteration":234,"passed_time":0.3390088107,"remaining_time":1.103581873},
{"learn":[1.363208227],"iteration":235,"passed_time":0.3400729659,"remaining_time":1.100914178},
{"learn":[1.35597396],"iteration":236,"passed_time":0.3411386678,"remaining_time":1.098264994},
{"learn":[1.348750542],"iteration":237,"passed_time":0.3423358588,"remaining_time":1.096050102},
{"learn":[1.340358766],"iteration":238,"passed_time":0.3434405512,"remaining_time":1.093549203},
{"learn":[1.332781432],"iteration":239,"passed_time":0.3445449757,"remaining_time":1.09105909},
{"learn":[1.327255841],"iteration":240,"passed_time":0.3456881668,"remaining_time":1.088702567},
{"learn":[1.320704606],"iteration":241,"passed_time":0.3468149014,"remaining_time":1.086304526},
{"learn":[1.31493707],"iteration":242,"passed_time":0.3479686187,"remaining_time":1.084001006},
{"learn":[1.309252819],"iteration":243,"passed_time":0.3494238513,"remaining_time":1.082641113},
{"learn":[1.303332558],"iteration":244,"passed_time":0.3507385412,"remaining_time":1.080847341},
{"learn":[1.296102134],"iteration":245,"passed_time":0.351899997,"remaining_time":1.078587796},
{"learn":[1.289159984],"iteration":246,"passed_time":0.3528047071,"remaining_time":1.075554431},
{"learn":[1.28376116],"iteration":247,"passed_time":0.3537723775,"remaining_time":1.072729145},
{"learn":[1.277863684],"iteration":248,"passed_time":0.3548283149,"remaining_time":1.070184998},
{"learn":[1.271336752],"iteration":249,"passed_time":0.3559885886,"remaining_time":1.067965766},
{"learn":[1.265977666],"iteration":250,"passed_time":0.3571808075,"remaining_time":1.065850298},
{"learn":[1.260604272],"iteration":251,"passed_time":0.3582609502,"remaining_time":1.063409487},
{"learn":[1.254397554],"iteration":252,"passed_time":0.3594110531,"remaining_time":1.061185995},
{"learn":[1.247322167],"iteration":253,"passed_time":0.36048234,"remaining_time":1.058739471},
{"learn":[1.242146955],"iteration":254,"passed_time":0.3616154749,"remaining_time":1.056484427},
{"learn":[1.237332319],"iteration":255,"passed_time":0.3628504993,"remaining_time":1.054534264},
{"learn":[1.230584502],"iteration":256,"passed_time":0.3643105618,"remaining_time":1.053240262},
{"learn":[1.224387257],"iteration":257,"passed_time":0.3658017819,"remaining_time":1.052034582},
{"learn":[1.218987355],"iteration":258,"passed_time":0.3668822847,"remaining_time":1.049651633},
{"learn":[1.214276062],"iteration":259,"passed_time":0.3680608748,"remaining_time":1.047557874},
{"learn":[1.207882913],"iteration":260,"passed_time":0.3691740834,"remaining_time":1.045286006},
{"learn":[1.201278883],"iteration":261,"passed_time":0.3701622191,"remaining_time":1.042670678},
{"learn":[1.195618429],"iteration":262,"passed_time":0.371220633,"remaining_time":1.040264664},
{"learn":[1.190486612],"iteration":263,"passed_time":0.3723378992,"remaining_time":1.038032931},
{"learn":[1.182993309],"iteration":264,"passed_time":0.37358739,"remaining_time":1.036176346},
{"learn":[1.178445745],"iteration":265,"passed_time":0.3745713467,"remaining_time":1.033591611},
{"learn":[1.173916183],"iteration":266,"passed_time":0.3755805566,"remaining_time":1.031088195},
{"learn":[1.169327158],"iteration":267,"passed_time":0.3766446097,"remaining_time":1.028745725},
{"learn":[1.164966809],"iteration":268,"passed_time":0.3777191657,"remaining_time":1.026441302},
{"learn":[1.160414383],"iteration":269,"passed_time":0.378695258,"remaining_time":1.023879772},
{"learn":[1.155882893],"iteration":270,"passed_time":0.3804801377,"remaining_time":1.02350561},
{"learn":[1.14953899],"iteration":271,"passed_time":0.3816150822,"remaining_time":1.021381544},
{"learn":[1.144181401],"iteration":272,"passed_time":0.3829408052,"remaining_time":1.019772767},
{"learn":[1.138808249],"iteration":273,"passed_time":0.3840344175,"remaining_time":1.017551048},
{"learn":[1.133712555],"iteration":274,"passed_time":0.3851189213,"remaining_time":1.01531352},
{"learn":[1.128084263],"iteration":275,"passed_time":0.3863506953,"remaining_time":1.013470664},
{"learn":[1.123782577],"iteration":276,"passed_time":0.3874201786,"remaining_time":1.011208625},
{"learn":[1.114372895],"iteration":277,"passed_time":0.3886019513,"remaining_time":1.009246794},
{"learn":[1.10986526],"iteration":278,"passed_time":0.3897299179,"remaining_time":1.007151508},
{"learn":[1.103994581],"iteration":279,"passed_time":0.3909185256,"remaining_time":1.005219066},
{"learn":[1.098191714],"iteration":280,"passed_time":0.3919675137,"remaining_time":1.00293467},
{"learn":[1.093630807],"iteration":281,"passed_time":0.3931002803,"remaining_time":1.000872345},
{"learn":[1.089659395],"iteration":282,"passed_time":0.3947982761,"remaining_time":1.000248636},
{"learn":[1.084392853],"iteration":283,"passed_time":0.3959554358,"remaining_time":0.9982538451},
{"learn":[1.080441565],"iteration":284,"passed_time":0.3970560263,"remaining_time":0.9961230134},
{"learn":[1.075067051],"iteration":285,"passed_time":0.397968831,"remaining_time":0.9935305782},
{"learn":[1.069327016],"iteration":286,"passed_time":0.3990784441,"remaining_time":0.9914387828},
{"learn":[1.064041505],"iteration":287,"passed_time":0.400093433,"remaining_time":0.9891198761},
{"learn":[1.060180153],"iteration":288,"passed_time":0.4011538403,"remaining_time":0.9869217317},
{"learn":[1.056290889],"iteration":289,"passed_time":0.4023795323,"remaining_time":0.9851360963},
{"learn":[1.050536748],"iteration":290,"passed_time":0.4034016404,"remaining_time":0.9828582922},
{"learn":[1.045126792],"iteration":291,"passed_time":0.4044436263,"remaining_time":0.9806372858},
{"learn":[1.041062328],"iteration":292,"passed_time":0.4055074549,"remaining_time":0.9784770328},
{"learn":[1.035960329],"iteration":293,"passed_time":0.4066198287,"remaining_time":0.9764408131},
{"learn":[1.031961122],"iteration":294,"passed_time":0.4077595603,"remaining_time":0.9744762374},
{"learn":[1.02836897],"iteration":295,"passed_time":0.4092769937,"remaining_time":0.9734155525},
{"learn":[1.024439836],"iteration":296,"passed_time":0.4103451211,"remaining_time":0.9712882834},
{"learn":[1.020663882],"iteration":297,"passed_time":0.4114276698,"remaining_time":0.9692020945},
{"learn":[1.015322049],"iteration":298,"passed_time":0.4123905472,"remaining_time":0.9668420522},
{"learn":[1.010122694],"iteration":299,"passed_time":0.4133939863,"remaining_time":0.9645859681},
{"learn":[1.005089145],"iteration":300,"passed_time":0.4143939634,"remaining_time":0.9623301676},
{"learn":[1.001573513],"iteration":301,"passed_time":0.4155829627,"remaining_time":0.9605195627},
{"learn":[0.9961611996],"iteration":302,"passed_time":0.4164916387,"remaining_time":0.958068225},
{"learn":[0.9909816409],"iteration":303,"passed_time":0.4176368842,"remaining_time":0.9561686559},
{"learn":[0.9868434823],"iteration":304,"passed_time":0.4187902653,"remaining_time":0.9542925718},
{"learn":[0.9834964207],"iteration":305,"passed_time":0.4197688545,"remaining_time":0.9520247877},
{"learn":[0.9800915282],"iteration":306,"passed_time":0.420872286,"remaining_time":0.9500472125},
{"learn":[0.9766533189],"iteration":307,"passed_time":0.4219923029,"remaining_time":0.9481125767},
{"learn":[0.9734222067],"iteration":308,"passed_time":0.4231363817,"remaining_time":0.9462370219},
{"learn":[0.9688483834],"iteration":309,"passed_time":0.4249366159,"remaining_time":0.9458266611},
{"learn":[0.9606892987],"iteration":310,"passed_time":0.4261864982,"remaining_time":0.9441880941},
{"learn":[0.9573078202],"iteration":311,"passed_time":0.4271464312,"remaining_time":0.9419126432},
{"learn":[0.9504340613],"iteration":312,"passed_time":0.4282243097,"remaining_time":0.9399044753},
{"learn":[0.9455474531],"iteration":313,"passed_time":0.429411059,"remaining_time":0.9381400844},
{"learn":[0.9412236418],"iteration":314,"passed_time":0.4306484093,"remaining_time":0.9364893981},
{"learn":[0.9362359829],"iteration":315,"passed_time":0.4318041568,"remaining_time":0.9346646938},
{"learn":[0.9313017555],"iteration":316,"passed_time":0.432933222,"remaining_time":0.9327867211},
{"learn":[0.9266180837],"iteration":317,"passed_time":0.4341768545,"remaining_time":0.931159166},
{"learn":[0.9236273305],"iteration":318,"passed_time":0.435364671,"remaining_time":0.9294148618},
{"learn":[0.9190828205],"iteration":319,"passed_time":0.4367164016,"remaining_time":0.9280223535},
{"learn":[0.9160140611],"iteration":320,"passed_time":0.4379589456,"remaining_time":0.9263991404},
{"learn":[0.9114459828],"iteration":321,"passed_time":0.4393861896,"remaining_time":0.9251671943},
{"learn":[0.9071397059],"iteration":322,"passed_time":0.4407985864,"remaining_time":0.9239029194},
{"learn":[0.9021342735],"iteration":323,"passed_time":0.4417566514,"remaining_time":0.9216898034},
{"learn":[0.8991007397],"iteration":324,"passed_time":0.4428860717,"remaining_time":0.9198403027},
{"learn":[0.8943238746],"iteration":325,"passed_time":0.4441859147,"remaining_time":0.9183475659},
{"learn":[0.8894133258],"iteration":326,"passed_time":0.4452193663,"remaining_time":0.9163077478},
{"learn":[0.8850592475],"iteration":327,"passed_time":0.4463380145,"remaining_time":0.914448615},
{"learn":[0.880614865],"iteration":328,"passed_time":0.4475229932,"remaining_time":0.9127292657},
{"learn":[0.8755399028],"iteration":329,"passed_time":0.4486045999,"remaining_time":0.9108032786},
{"learn":[0.8726688312],"iteration":330,"passed_time":0.4496622662,"remaining_time":0.9088340062},
{"learn":[0.8683109699],"iteration":331,"passed_time":0.4508679368,"remaining_time":0.9071680175},
{"learn":[0.863629412],"iteration":332,"passed_time":0.4522376195,"remaining_time":0.9058333099},
{"learn":[0.8589611265],"iteration":333,"passed_time":0.453786499,"remaining_time":0.9048557136},
{"learn":[0.8519054185],"iteration":334,"passed_time":0.455493654,"remaining_time":0.9041888953},
{"learn":[0.8492568191],"iteration":335,"passed_time":0.4565769175,"remaining_time":0.902282956},
{"learn":[0.8432462865],"iteration":336,"passed_time":0.4578926874,"remaining_time":0.9008393228},
{"learn":[0.8406503596],"iteration":337,"passed_time":0.4590341562,"remaining_time":0.8990550632},
{"learn":[0.8361394924],"iteration":338,"passed_time":0.4603194032,"remaining_time":0.8975549425},
{"learn":[0.8294857069],"iteration":339,"passed_time":0.4614492999,"remaining_time":0.8957545234},
{"learn":[0.8236638016],"iteration":340,"passed_time":0.4626122936,"remaining_time":0.8940219985},
{"learn":[0.8196084054],"iteration":341,"passed_time":0.4637363175,"remaining_time":0.8922178273},
{"learn":[0.8155793216],"iteration":342,"passed_time":0.4651977356,"remaining_time":0.8910638842},
{"learn":[0.8099416611],"iteration":343,"passed_time":0.4667716478,"remaining_time":0.8901226772},
{"learn":[0.8055977471],"iteration":344,"passed_time":0.4684604582,"remaining_time":0.8893959424},
{"learn":[0.7999968483],"iteration":345,"passed_time":0.4700582748,"remaining_time":0.8884916524},
{"learn":[0.7961042979],"iteration":346,"passed_time":0.4715819408,"remaining_time":0.8874438252},
{"learn":[0.7906350798],"iteration":347,"passed_time":0.4731766734,"remaining_time":0.8865264111},
{"learn":[0.786415178],"iteration":348,"passed_time":0.4742707155,"remaining_time":0.8846711626},
{"learn":[0.7807428392],"iteration":349,"passed_time":0.4753386288,"remaining_time":0.8827717392},
{"learn":[0.7769617757],"iteration":350,"passed_time":0.4764289408,"remaining_time":0.8809184689},
{"learn":[0.7728330961],"iteration":351,"passed_time":0.477482458,"remaining_time":0.8790017977},
{"learn":[0.769331411],"iteration":352,"passed_time":0.4786822858,"remaining_time":0.8773581839},
{"learn":[0.7656353056],"iteration":353,"passed_time":0.4803202582,"remaining_time":0.8765166294},
{"learn":[0.7615644685],"iteration":354,"passed_time":0.4814542384,"remaining_time":0.8747548838},
{"learn":[0.756160645],"iteration":355,"passed_time":0.4829327997,"remaining_time":0.8736200084},
{"learn":[0.7522059767],"iteration":356,"passed_time":0.4844727209,"remaining_time":0.8725937242},
{"learn":[0.7475538859],"iteration":357,"passed_time":0.4857433612,"remaining_time":0.8710816701},
{"learn":[0.7425563899],"iteration":358,"passed_time":0.4869337195,"remaining_time":0.8694276162},
{"learn":[0.7386401572],"iteration":359,"passed_time":0.487974032,"remaining_time":0.8675093901},
{"learn":[0.7334589894],"iteration":360,"passed_time":0.4889656714,"remaining_time":0.8655098726},
{"learn":[0.7289725382],"iteration":361,"passed_time":0.4899592292,"remaining_time":0.8635193045},
{"learn":[0.723677515],"iteration":362,"passed_time":0.4910192435,"remaining_time":0.8616508488},
{"learn":[0.718483203],"iteration":363,"passed_time":0.4922136102,"remaining_time":0.8600215827},
{"learn":[0.7147315545],"iteration":364,"passed_time":0.4934325474,"remaining_time":0.8584374455},
{"learn":[0.7113627007],"iteration":365,"passed_time":0.4947295845,"remaining_time":0.8569905917},
{"learn":[0.7080230498],"iteration":366,"passed_time":0.4957316923,"remaining_time":0.8550358616},
{"learn":[0.7045746237],"iteration":367,"passed_time":0.4969308901,"remaining_time":0.8534247895},
{"learn":[0.7014202403],"iteration":368,"passed_time":0.4984056818,"remaining_time":0.8522872228},
{"learn":[0.6976397544],"iteration":369,"passed_time":0.4996029787,"remaining_time":0.8506753422},
{"learn":[0.6939098509],"iteration":370,"passed_time":0.5009106301,"remaining_time":0.8492527934},
{"learn":[0.6902158338],"iteration":371,"passed_time":0.5020179401,"remaining_time":0.8474926516},
{"learn":[0.6865435523],"iteration":372,"passed_time":0.5029873686,"remaining_time":0.8455042363},
{"learn":[0.6829202566],"iteration":373,"passed_time":0.5040790722,"remaining_time":0.8437259337},
{"learn":[0.6793317062],"iteration":374,"passed_time":0.5052466889,"remaining_time":0.8420778149},
{"learn":[0.6757775333],"iteration":375,"passed_time":0.5063544522,"remaining_time":0.8403329206},
{"learn":[0.6722441356],"iteration":376,"passed_time":0.5074772662,"remaining_time":0.838616278},
{"learn":[0.6687577367],"iteration":377,"passed_time":0.508561221,"remaining_time":0.8368388345},
{"learn":[0.6653046463],"iteration":378,"passed_time":0.5094671371,"remaining_time":0.8347733301},
{"learn":[0.6618716911],"iteration":379,"passed_time":0.5104232358,"remaining_time":0.8327958059},
{"learn":[0.658484285],"iteration":380,"passed_time":0.5114682516,"remaining_time":0.8309681042},
{"learn":[0.6551291681],"iteration":381,"passed_time":0.5126267614,"remaining_time":0.8293281114},
{"learn":[0.6518060112],"iteration":382,"passed_time":0.5142079649,"remaining_time":0.8283715778},
{"learn":[0.6485144902],"iteration":383,"passed_time":0.5155050397,"remaining_time":0.8269560012},
{"learn":[0.645254286],"iteration":384,"passed_time":0.5166973189,"remaining_time":0.8253736393},
{"learn":[0.6420250841],"iteration":385,"passed_time":0.5177031218,"remaining_time":0.8234966756},
{"learn":[0.6388265749],"iteration":386,"passed_time":0.518848146,"remaining_time":0.8218447377},
{"learn":[0.6356584534],"iteration":387,"passed_time":0.5197638324,"remaining_time":0.8198336737},
{"learn":[0.6325204189],"iteration":388,"passed_time":0.5207878182,"remaining_time":0.8179983468},
{"learn":[0.6294121752],"iteration":389,"passed_time":0.5219570177,"remaining_time":0.8163943097},
{"learn":[0.6263217492],"iteration":390,"passed_time":0.5230258076,"remaining_time":0.8146361044},
{"learn":[0.6232723069],"iteration":391,"passed_time":0.524157702,"remaining_time":0.8129792929},
{"learn":[0.6202517916],"iteration":392,"passed_time":0.525253495,"remaining_time":0.811269393},
{"learn":[0.617259924],"iteration":393,"passed_time":0.5263706138,"remaining_time":0.8095954111},
{"learn":[0.6142964282],"iteration":394,"passed_time":0.5276197531,"remaining_time":0.8081264573},
{"learn":[0.6113610325],"iteration":395,"passed_time":0.5288993043,"remaining_time":0.8067049994},
{"learn":[0.6084788222],"iteration":396,"passed_time":0.5300417377,"remaining_time":0.8050759895},
{"learn":[0.6055914014],"iteration":397,"passed_time":0.531113617,"remaining_time":0.8033427071},
{"learn":[0.6027562437],"iteration":398,"passed_time":0.5320915826,"remaining_time":0.8014712811},
{"learn":[0.5999477647],"iteration":399,"passed_time":0.5331729485,"remaining_time":0.7997594227},
{"learn":[0.5971272785],"iteration":400,"passed_time":0.5342007967,"remaining_time":0.7979707661},
{"learn":[0.5943647451],"iteration":401,"passed_time":0.5353011038,"remaining_time":0.7962936818},
{"learn":[0.5915905365],"iteration":402,"passed_time":0.5364208356,"remaining_time":0.7946482353},
{"learn":[0.5888732638],"iteration":403,"passed_time":0.537681329,"remaining_time":0.7932130498},
{"learn":[0.5861816649],"iteration":404,"passed_time":0.5388136952,"remaining_time":0.7915904905},
{"learn":[0.5834719655],"iteration":405,"passed_time":0.539823993,"remaining_time":0.7897917533},
{"learn":[0.5808245678],"iteration":406,"passed_time":0.5408626808,"remaining_time":0.7880382548},
{"learn":[0.5782022478],"iteration":407,"passed_time":0.5418798007,"remaining_time":0.7862569658},
{"learn":[0.5755556613],"iteration":408,"passed_time":0.5431674312,"remaining_time":0.7848702979},
{"learn":[0.5729346116],"iteration":409,"passed_time":0.5443649723,"remaining_time":0.7833544723},
{"learn":[0.5703736487],"iteration":410,"passed_time":0.5453668702,"remaining_time":0.7815598213},
{"learn":[0.5678370383],"iteration":411,"passed_time":0.5463822314,"remaining_time":0.7797882331},
{"learn":[0.5652772537],"iteration":412,"passed_time":0.5474140394,"remaining_time":0.7780436832},
{"learn":[0.5627422891],"iteration":413,"passed_time":0.5484761698,"remaining_time":0.7763454965},
{"learn":[0.5602652198],"iteration":414,"passed_time":0.5494919746,"remaining_time":0.7745850727},
{"learn":[0.5577723587],"iteration":415,"passed_time":0.5507574284,"remaining_time":0.7731786976},
{"learn":[0.556073245],"iteration":416,"passed_time":0.5519025033,"remaining_time":0.7716046988},
{"learn":[0.5536475262],"iteration":417,"passed_time":0.5530067653,"remaining_time":0.7699759268},
{"learn":[0.5512450488],"iteration":418,"passed_time":0.5540314595,"remaining_time":0.768239327},
{"learn":[0.5488196622],"iteration":419,"passed_time":0.5550875297,"remaining_time":0.7665494458},
{"learn":[0.5464571355],"iteration":420,"passed_time":0.5560756325,"remaining_time":0.7647691003},
{"learn":[0.5430555004],"iteration":421,"passed_time":0.5575773738,"remaining_time":0.7636960238},
{"learn":[0.5407361861],"iteration":422,"passed_time":0.5588981957,"remaining_time":0.7623741346},
{"learn":[0.53739995],"iteration":423,"passed_time":0.5601306821,"remaining_time":0.7609322474},
{"learn":[0.5351231031],"iteration":424,"passed_time":0.5616482489,"remaining_time":0.7598770427},
{"learn":[0.5318511716],"iteration":425,"passed_time":0.5627152236,"remaining_time":0.7582125314},
{"learn":[0.5296160598],"iteration":426,"passed_time":0.5637664641,"remaining_time":0.7565297048},
{"learn":[0.5268866058],"iteration":427,"passed_time":0.5647871703,"remaining_time":0.754809022},
{"learn":[0.5246894971],"iteration":428,"passed_time":0.5658245572,"remaining_time":0.7531138045},
{"learn":[0.522007282],"iteration":429,"passed_time":0.5669170959,"remaining_time":0.751494755},
{"learn":[0.5198475687],"iteration":430,"passed_time":0.5679444684,"remaining_time":0.7497921172},
{"learn":[0.5167381178],"iteration":431,"passed_time":0.5691535378,"remaining_time":0.7483315034},
{"learn":[0.5146181357],"iteration":432,"passed_time":0.5703201841,"remaining_time":0.7468164997},
{"learn":[0.5120279914],"iteration":433,"passed_time":0.5714820214,"remaining_time":0.7452968297},
{"learn":[0.5099441794],"iteration":434,"passed_time":0.5728062946,"remaining_time":0.743989785},
{"learn":[0.5073991271],"iteration":435,"passed_time":0.5742387976,"remaining_time":0.7428226648},
{"learn":[0.5040687121],"iteration":436,"passed_time":0.5753918618,"remaining_time":0.7412943209},
{"learn":[0.5020374541],"iteration":437,"passed_time":0.5764086081,"remaining_time":0.7395927803},
{"learn":[0.4987650552],"iteration":438,"passed_time":0.5774735931,"remaining_time":0.7379560039},
{"learn":[0.4967702634],"iteration":439,"passed_time":0.578541651,"remaining_time":0.7363257376},
{"learn":[0.4935549503],"iteration":440,"passed_time":0.5798799806,"remaining_time":0.7350406103},
{"learn":[0.4915959966],"iteration":441,"passed_time":0.5810647344,"remaining_time":0.7335613615},
{"learn":[0.4884368548],"iteration":442,"passed_time":0.5823068358,"remaining_time":0.7321555475},
{"learn":[0.4865131232],"iteration":443,"passed_time":0.5833525397,"remaining_time":0.7305045317},
{"learn":[0.4841384957],"iteration":444,"passed_time":0.5843756243,"remaining_time":0.7288280258},
{"learn":[0.4810545344],"iteration":445,"passed_time":0.5853798039,"remaining_time":0.7271309672},
{"learn":[0.4780091953],"iteration":446,"passed_time":0.586943172,"remaining_time":0.7261288012},
{"learn":[0.4760560656],"iteration":447,"passed_time":0.5882747183,"remaining_time":0.7248384922},
{"learn":[0.4730663028],"iteration":448,"passed_time":0.589832367,"remaining_time":0.7238254659},
{"learn":[0.4712882029],"iteration":449,"passed_time":0.5909581833,"remaining_time":0.722282224},
{"learn":[0.4686749516],"iteration":450,"passed_time":0.5921350584,"remaining_time":0.7208029869},
{"learn":[0.4660000324],"iteration":451,"passed_time":0.5932598025,"remaining_time":0.7192618845},
{"learn":[0.463365511],"iteration":452,"passed_time":0.59434836,"remaining_time":0.7176789248},
{"learn":[0.4607707673],"iteration":453,"passed_time":0.5958953444,"remaining_time":0.716649467},
{"learn":[0.4582151903],"iteration":454,"passed_time":0.597096775,"remaining_time":0.7152038294},
{"learn":[0.4559313104],"iteration":455,"passed_time":0.5981916101,"remaining_time":0.7136320963},
{"learn":[0.4535884603],"iteration":456,"passed_time":0.599266603,"remaining_time":0.7120388741},
{"learn":[0.4513484],"iteration":457,"passed_time":0.6003062198,"remaining_time":0.7104060505},
{"learn":[0.4488506869],"iteration":458,"passed_time":0.6021682086,"remaining_time":0.7097451},
{"learn":[0.4466481621],"iteration":459,"passed_time":0.6038491404,"remaining_time":0.7088663822},
{"learn":[0.4454644724],"iteration":460,"passed_time":0.6049919175,"remaining_time":0.7073549751},
{"learn":[0.4429667477],"iteration":461,"passed_time":0.6060447013,"remaining_time":0.7057403664},
{"learn":[0.4407074752],"iteration":462,"passed_time":0.6071318215,"remaining_time":0.7041680089},
{"learn":[0.4385582467],"iteration":463,"passed_time":0.6081597971,"remaining_time":0.7025294208},
{"learn":[0.4363290172],"iteration":464,"passed_time":0.6093360113,"remaining_time":0.701064013},
{"learn":[0.434120113],"iteration":465,"passed_time":0.610482759,"remaining_time":0.69956608},
{"learn":[0.4317046575],"iteration":466,"passed_time":0.6116543898,"remaining_time":0.6980980509},
{"learn":[0.4296105051],"iteration":467,"passed_time":0.6128493129,"remaining_time":0.696657766},
{"learn":[0.427446303],"iteration":468,"passed_time":0.6141204208,"remaining_time":0.6953047835},
{"learn":[0.4250803412],"iteration":469,"passed_time":0.6155874237,"remaining_time":0.6941730523},
{"learn":[0.4230308181],"iteration":470,"passed_time":0.6168284705,"remaining_time":0.6927861165},
{"learn":[0.4219335338],"iteration":471,"passed_time":0.619277843,"remaining_time":0.6927514853},
{"learn":[0.4198201381],"iteration":472,"passed_time":0.6202585861,"remaining_time":0.6910703485},
{"learn":[0.4169608618],"iteration":473,"passed_time":0.6212726392,"remaining_time":0.6894291312},
{"learn":[0.4158942051],"iteration":474,"passed_time":0.6223098904,"remaining_time":0.6878161946},
{"learn":[0.4136065137],"iteration":475,"passed_time":0.6233782128,"remaining_time":0.6862398813},
{"learn":[0.4108854832],"iteration":476,"passed_time":0.6245321778,"remaining_time":0.6847595996},
{"learn":[0.4081983916],"iteration":477,"passed_time":0.6257663035,"remaining_time":0.6833682226},
{"learn":[0.405544817],"iteration":478,"passed_time":0.6270480275,"remaining_time":0.6820292741},
{"learn":[0.4029243436],"iteration":479,"passed_time":0.628255619,"remaining_time":0.6806102539},
{"learn":[0.4003365618],"iteration":480,"passed_time":0.6296387777,"remaining_time":0.6793815501},
{"learn":[0.3985145281],"iteration":481,"passed_time":0.6312421753,"remaining_time":0.6783888937},
{"learn":[0.3956644744],"iteration":482,"passed_time":0.6327803302,"remaining_time":0.6773238731},
{"learn":[0.3938861089],"iteration":483,"passed_time":0.6338855648,"remaining_time":0.6757953542},
{"learn":[0.3913688368],"iteration":484,"passed_time":0.6351029241,"remaining_time":0.674387641},
{"learn":[0.3885897995],"iteration":485,"passed_time":0.6362833608,"remaining_time":0.6729416614},
{"learn":[0.3868605749],"iteration":486,"passed_time":0.6375106082,"remaining_time":0.6715460821},
{"learn":[0.3844052339],"iteration":487,"passed_time":0.6387842868,"remaining_time":0.6701999075},
{"learn":[0.3827176145],"iteration":488,"passed_time":0.6399584188,"remaining_time":0.6687500041},
{"learn":[0.3800139321],"iteration":489,"passed_time":0.6410931581,"remaining_time":0.6672602257},
{"learn":[0.3773487154],"iteration":490,"passed_time":0.6424621512,"remaining_time":0.6660147351},
{"learn":[0.3757752232],"iteration":491,"passed_time":0.6435963865,"remaining_time":0.6645263503},
{"learn":[0.3734088591],"iteration":492,"passed_time":0.6454540168,"remaining_time":0.6637833398},
{"learn":[0.3718039571],"iteration":493,"passed_time":0.646759742,"remaining_time":0.6624705049},
{"learn":[0.369210601],"iteration":494,"passed_time":0.6480130049,"remaining_time":0.6611041767},
{"learn":[0.3669023279],"iteration":495,"passed_time":0.649257802,"remaining_time":0.6597297021},
{"learn":[0.3654052374],"iteration":496,"passed_time":0.6504165378,"remaining_time":0.658268649},
{"learn":[0.3628761819],"iteration":497,"passed_time":0.6514080631,"remaining_time":0.6566402563},
{"learn":[0.3614162998],"iteration":498,"passed_time":0.6524783195,"remaining_time":0.655093463},
{"learn":[0.3591706701],"iteration":499,"passed_time":0.6535920324,"remaining_time":0.6535920324},
{"learn":[0.3569534257],"iteration":500,"passed_time":0.6546625893,"remaining_time":0.6520491658},
{"learn":[0.3555302676],"iteration":501,"passed_time":0.65592835,"remaining_time":0.6507018293},
{"learn":[0.3530934391],"iteration":502,"passed_time":0.6571458692,"remaining_time":0.6493071511},
{"learn":[0.3517000521],"iteration":503,"passed_time":0.6582500449,"remaining_time":0.6478016315},
{"learn":[0.3495442266],"iteration":504,"passed_time":0.6595370975,"remaining_time":0.6464769569},
{"learn":[0.3481796402],"iteration":505,"passed_time":0.6607816419,"remaining_time":0.6451109311},
{"learn":[0.3456098862],"iteration":506,"passed_time":0.6619262036,"remaining_time":0.6436481625},
{"learn":[0.3435079444],"iteration":507,"passed_time":0.6629720969,"remaining_time":0.642091086},
{"learn":[0.3421769548],"iteration":508,"passed_time":0.6638451128,"remaining_time":0.6403692542},
{"learn":[0.3401074635],"iteration":509,"passed_time":0.6648390792,"remaining_time":0.6387669585},
{"learn":[0.3388038213],"iteration":510,"passed_time":0.6664404628,"remaining_time":0.6377483098},
{"learn":[0.336512921],"iteration":511,"passed_time":0.6676457362,"remaining_time":0.6363498423},
{"learn":[0.3344949179],"iteration":512,"passed_time":0.6687674323,"remaining_time":0.6348727866},
{"learn":[0.3332238383],"iteration":513,"passed_time":0.6698377962,"remaining_time":0.6333485777},
{"learn":[0.3307947772],"iteration":514,"passed_time":0.6708687573,"remaining_time":0.6317890239},
{"learn":[0.3292941771],"iteration":515,"passed_time":0.6720494503,"remaining_time":0.630371965},
{"learn":[0.327331088],"iteration":516,"passed_time":0.6730327624,"remaining_time":0.6287714202},
{"learn":[0.3253930779],"iteration":517,"passed_time":0.674096545,"remaining_time":0.6272481364},
{"learn":[0.3241790252],"iteration":518,"passed_time":0.6751909343,"remaining_time":0.6257549892},
{"learn":[0.3218367365],"iteration":519,"passed_time":0.6770316658,"remaining_time":0.6249523069},
{"learn":[0.3199469743],"iteration":520,"passed_time":0.6782676834,"remaining_time":0.6235896744},
{"learn":[0.3185148726],"iteration":521,"passed_time":0.679396912,"remaining_time":0.6221297394},
{"learn":[0.3164055772],"iteration":522,"passed_time":0.6806859755,"remaining_time":0.6208168457},
{"learn":[0.315246272],"iteration":523,"passed_time":0.6818197896,"remaining_time":0.619363015},
{"learn":[0.3132251644],"iteration":524,"passed_time":0.6829786207,"remaining_time":0.6179330378},
{"learn":[0.3116250356],"iteration":525,"passed_time":0.6840028652,"remaining_time":0.6163828101},
{"learn":[0.3102542514],"iteration":526,"passed_time":0.6851140359,"remaining_time":0.6149125977},
{"learn":[0.3084532361],"iteration":527,"passed_time":0.6861772706,"remaining_time":0.6134008934},
{"learn":[0.3073440274],"iteration":528,"passed_time":0.6873216987,"remaining_time":0.611963176},
{"learn":[0.3063694844],"iteration":529,"passed_time":0.688485715,"remaining_time":0.6105439359},
{"learn":[0.3048199179],"iteration":530,"passed_time":0.689923841,"remaining_time":0.6093677617},
{"learn":[0.3038609606],"iteration":531,"passed_time":0.6913286082,"remaining_time":0.6081612568},
{"learn":[0.3023388346],"iteration":532,"passed_time":0.6926267406,"remaining_time":0.6068605776},
{"learn":[0.3010284591],"iteration":533,"passed_time":0.6937011689,"remaining_time":0.6053646904},
{"learn":[0.3000875245],"iteration":534,"passed_time":0.6946419507,"remaining_time":0.6037542188},
{"learn":[0.2983625567],"iteration":535,"passed_time":0.695909502,"remaining_time":0.6024291211},
{"learn":[0.2970839833],"iteration":536,"passed_time":0.6971252367,"remaining_time":0.6010595616},
{"learn":[0.296161037],"iteration":537,"passed_time":0.6983679538,"remaining_time":0.5997137447},
{"learn":[0.2946910443],"iteration":538,"passed_time":0.699445455,"remaining_time":0.5982270033},
{"learn":[0.2928285292],"iteration":539,"passed_time":0.7006054525,"remaining_time":0.5968120521},
{"learn":[0.2919275942],"iteration":540,"passed_time":0.7016983428,"remaining_time":0.5953411078},
{"learn":[0.2904864794],"iteration":541,"passed_time":0.7028311141,"remaining_time":0.5939052588},
{"learn":[0.2886674491],"iteration":542,"passed_time":0.7039739776,"remaining_time":0.5924790198},
{"learn":[0.2868493281],"iteration":543,"passed_time":0.7054100689,"remaining_time":0.5912996166},
{"learn":[0.2850695842],"iteration":544,"passed_time":0.7069265268,"remaining_time":0.5901863664},
{"learn":[0.2832838077],"iteration":545,"passed_time":0.708038746,"remaining_time":0.5887355141},
{"learn":[0.2819651804],"iteration":546,"passed_time":0.7091145409,"remaining_time":0.587255735},
{"learn":[0.2806212835],"iteration":547,"passed_time":0.7102598321,"remaining_time":0.585834752},
{"learn":[0.2794486311],"iteration":548,"passed_time":0.7115312601,"remaining_time":0.584518394},
{"learn":[0.2780773191],"iteration":549,"passed_time":0.7128871141,"remaining_time":0.5832712752},
{"learn":[0.2767941998],"iteration":550,"passed_time":0.714183871,"remaining_time":0.5819756045},
{"learn":[0.274671255],"iteration":551,"passed_time":0.715338643,"remaining_time":0.5805646957},
{"learn":[0.2736474893],"iteration":552,"passed_time":0.7163868865,"remaining_time":0.5790686045},
{"learn":[0.2726359307],"iteration":553,"passed_time":0.7175759361,"remaining_time":0.5776874865},
{"learn":[0.2719910234],"iteration":554,"passed_time":0.7186948302,"remaining_time":0.5762508098},
{"learn":[0.2698581783],"iteration":555,"passed_time":0.7206283122,"remaining_time":0.5754657745},
{"learn":[0.2677628316],"iteration":556,"passed_time":0.7224956496,"remaining_time":0.5746240086},
{"learn":[0.2663101327],"iteration":557,"passed_time":0.7235838758,"remaining_time":0.5731614214},
{"learn":[0.2653355764],"iteration":558,"passed_time":0.7246977069,"remaining_time":0.5717203734},
{"learn":[0.2643527974],"iteration":559,"passed_time":0.7257181443,"remaining_time":0.5702071134},
{"learn":[0.2633856261],"iteration":560,"passed_time":0.7268728981,"remaining_time":0.568800717},
{"learn":[0.2613631987],"iteration":561,"passed_time":0.7280620037,"remaining_time":0.5674219886},
{"learn":[0.2603594898],"iteration":562,"passed_time":0.7291910396,"remaining_time":0.5659973078},
{"learn":[0.2593694404],"iteration":563,"passed_time":0.7303836368,"remaining_time":0.5646228114},
{"learn":[0.2583928633],"iteration":564,"passed_time":0.7315328036,"remaining_time":0.5632155214},
{"learn":[0.2574295741],"iteration":565,"passed_time":0.7326235136,"remaining_time":0.5617643196},
{"learn":[0.2564793907],"iteration":566,"passed_time":0.7338606066,"remaining_time":0.5604261775},
{"learn":[0.2555421337],"iteration":567,"passed_time":0.7351794587,"remaining_time":0.5591505743},
{"learn":[0.254179538],"iteration":568,"passed_time":0.7364897384,"remaining_time":0.5578683256},
{"learn":[0.2532604348],"iteration":569,"passed_time":0.7376285246,"remaining_time":0.5564566063},
{"learn":[0.2523538544],"iteration":570,"passed_time":0.7387655138,"remaining_time":0.5550444929},
{"learn":[0.2504560591],"iteration":571,"passed_time":0.7398265946,"remaining_time":0.5535765428},
{"learn":[0.2495686251],"iteration":572,"passed_time":0.7408260541,"remaining_time":0.5520640927},
{"learn":[0.2486932938],"iteration":573,"passed_time":0.7420502214,"remaining_time":0.5507201992},
{"learn":[0.2473966041],"iteration":574,"passed_time":0.7432269335,"remaining_time":0.5493416465},
{"learn":[0.2461794874],"iteration":575,"passed_time":0.7438875895,"remaining_time":0.54758392},
{"learn":[0.2452962886],"iteration":576,"passed_time":0.7450793915,"remaining_time":0.5462193806},
{"learn":[0.2444520972],"iteration":577,"passed_time":0.746210435,"remaining_time":0.5448110788},
{"learn":[0.2435905945],"iteration":578,"passed_time":0.74733445,"remaining_time":0.5433986242},
{"learn":[0.242706397],"iteration":579,"passed_time":0.7486483137,"remaining_time":0.5421246409},
{"learn":[0.2418878808],"iteration":580,"passed_time":0.7498827191,"remaining_time":0.5407932174},
{"learn":[0.241053644],"iteration":581,"passed_time":0.751206679,"remaining_time":0.5395264464},
{"learn":[0.2398988616],"iteration":582,"passed_time":0.7518954998,"remaining_time":0.537805186},
{"learn":[0.2390706286],"iteration":583,"passed_time":0.753074283,"remaining_time":0.5364364756},
{"learn":[0.2382795033],"iteration":584,"passed_time":0.754122523,"remaining_time":0.5349758069},
{"learn":[0.2372787831],"iteration":585,"passed_time":0.7552400848,"remaining_time":0.5335655206},
{"learn":[0.2364806335],"iteration":586,"passed_time":0.7563594682,"remaining_time":0.5321575134},
{"learn":[0.235717458],"iteration":587,"passed_time":0.7574918433,"remaining_time":0.5307595909},
{"learn":[0.2349445669],"iteration":588,"passed_time":0.7586642293,"remaining_time":0.5293904894},
{"learn":[0.2333586885],"iteration":589,"passed_time":0.7597527475,"remaining_time":0.5279637737},
{"learn":[0.2325867562],"iteration":590,"passed_time":0.7611035274,"remaining_time":0.5267197},
{"learn":[0.2310273976],"iteration":591,"passed_time":0.7622845687,"remaining_time":0.5253582838},
{"learn":[0.2302469488],"iteration":592,"passed_time":0.7636152484,"remaining_time":0.5241001789},
{"learn":[0.2294912932],"iteration":593,"passed_time":0.764918739,"remaining_time":0.5228232458},
{"learn":[0.2279574202],"iteration":594,"passed_time":0.7660630072,"remaining_time":0.5214378453},
{"learn":[0.2271950999],"iteration":595,"passed_time":0.7670550514,"remaining_time":0.5199500684},
{"learn":[0.2257912917],"iteration":596,"passed_time":0.7680722999,"remaining_time":0.5184809662},
{"learn":[0.2248802989],"iteration":597,"passed_time":0.7691523344,"remaining_time":0.5170555827},
{"learn":[0.2239896932],"iteration":598,"passed_time":0.7702641215,"remaining_time":0.5156526089},
{"learn":[0.2232704436],"iteration":599,"passed_time":0.7712794691,"remaining_time":0.5141863127},
{"learn":[0.2219020141],"iteration":600,"passed_time":0.7724137793,"remaining_time":0.5128004958},
{"learn":[0.2202847927],"iteration":601,"passed_time":0.7736141342,"remaining_time":0.5114591784},
{"learn":[0.2186947484],"iteration":602,"passed_time":0.7746599166,"remaining_time":0.510016562},
{"learn":[0.2172157694],"iteration":603,"passed_time":0.7761062579,"remaining_time":0.5088378777},
{"learn":[0.2157594249],"iteration":604,"passed_time":0.7772781532,"remaining_time":0.5074791248},
{"learn":[0.2144513544],"iteration":605,"passed_time":0.778608483,"remaining_time":0.5062239972},
{"learn":[0.2129154788],"iteration":606,"passed_time":0.7797511927,"remaining_time":0.5048471478},
{"learn":[0.2114053389],"iteration":607,"passed_time":0.7807681,"remaining_time":0.5033899592},
{"learn":[0.2099204906],"iteration":608,"passed_time":0.7818771906,"remaining_time":0.5019934015},
{"learn":[0.208515654],"iteration":609,"passed_time":0.7830886313,"remaining_time":0.5006632233},
{"learn":[0.2071323995],"iteration":610,"passed_time":0.7840432886,"remaining_time":0.4991699497},
{"learn":[0.2055897751],"iteration":611,"passed_time":0.7852765827,"remaining_time":0.4978550884},
{"learn":[0.2043643644],"iteration":612,"passed_time":0.7863160667,"remaining_time":0.4964181367},
{"learn":[0.2035257121],"iteration":613,"passed_time":0.7875055214,"remaining_time":0.495076761},
{"learn":[0.2027160211],"iteration":614,"passed_time":0.7890102106,"remaining_time":0.4939332213},
{"learn":[0.2019244206],"iteration":615,"passed_time":0.7900956309,"remaining_time":0.4925271465},
{"learn":[0.2012916401],"iteration":616,"passed_time":0.7911911245,"remaining_time":0.4911283642},
{"learn":[0.2004711673],"iteration":617,"passed_time":0.7922210445,"remaining_time":0.4896900308},
{"learn":[0.1998495103],"iteration":618,"passed_time":0.7935643041,"remaining_time":0.4884458802},
{"learn":[0.1991957274],"iteration":619,"passed_time":0.7947435965,"remaining_time":0.487100914},
{"learn":[0.1985458582],"iteration":620,"passed_time":0.7957108661,"remaining_time":0.4856270825},
{"learn":[0.1973268236],"iteration":621,"passed_time":0.7967344836,"remaining_time":0.4841891234},
{"learn":[0.1966738876],"iteration":622,"passed_time":0.7979099568,"remaining_time":0.482844388},
{"learn":[0.1957538441],"iteration":623,"passed_time":0.7990311943,"remaining_time":0.4814675145},
{"learn":[0.1951126082],"iteration":624,"passed_time":0.8000249766,"remaining_time":0.480014986},
{"learn":[0.1938565088],"iteration":625,"passed_time":0.8010435342,"remaining_time":0.4785787249},
{"learn":[0.1925726156],"iteration":626,"passed_time":0.8021192877,"remaining_time":0.4771778219},
{"learn":[0.1913086685],"iteration":627,"passed_time":0.803191879,"remaining_time":0.4757760812},
{"learn":[0.1901677526],"iteration":628,"passed_time":0.8042630074,"remaining_time":0.4743745242},
{"learn":[0.1889839981],"iteration":629,"passed_time":0.8053865494,"remaining_time":0.4730047989},
{"learn":[0.1883781839],"iteration":630,"passed_time":0.8065612732,"remaining_time":0.4716657841},
{"learn":[0.1872283545],"iteration":631,"passed_time":0.8077115724,"remaining_time":0.4703130675},
{"learn":[0.1866336796],"iteration":632,"passed_time":0.8090447654,"remaining_time":0.4690670283},
{"learn":[0.1852746828],"iteration":633,"passed_time":0.8102753916,"remaining_time":0.4677615037},
{"learn":[0.1841885715],"iteration":634,"passed_time":0.8113807097,"remaining_time":0.4663841875},
{"learn":[0.1836093971],"iteration":635,"passed_time":0.812357342,"remaining_time":0.4649340762},
{"learn":[0.1825479791],"iteration":636,"passed_time":0.8133597521,"remaining_time":0.4635001413},
{"learn":[0.1819164854],"iteration":637,"passed_time":0.8143591468,"remaining_time":0.4620658482},
{"learn":[0.1811123967],"iteration":638,"passed_time":0.8155288349,"remaining_time":0.4607291227},
{"learn":[0.1804923139],"iteration":639,"passed_time":0.8165444281,"remaining_time":0.4593062408},
{"learn":[0.1794680828],"iteration":640,"passed_time":0.8175293074,"remaining_time":0.457867428},
{"learn":[0.1786882426],"iteration":641,"passed_time":0.8186473531,"remaining_time":0.4565042872},
{"learn":[0.1784214207],"iteration":642,"passed_time":0.8197066347,"remaining_time":0.4551092824},
{"learn":[0.1781575854],"iteration":643,"passed_time":0.8208064436,"remaining_time":0.4537377235},
{"learn":[0.1773890821],"iteration":644,"passed_time":0.8218570584,"remaining_time":0.4523399314},
{"learn":[0.1771283242],"iteration":645,"passed_time":0.8233112634,"remaining_time":0.4511643766},
{"learn":[0.1761426951],"iteration":646,"passed_time":0.8244568387,"remaining_time":0.4498195735},
{"learn":[0.1755489515],"iteration":647,"passed_time":0.8255279945,"remaining_time":0.44843496},
{"learn":[0.1748037897],"iteration":648,"passed_time":0.8265196782,"remaining_time":0.4470083314},
{"learn":[0.1745477458],"iteration":649,"passed_time":0.8275001983,"remaining_time":0.4455770298},
{"learn":[0.1738132795],"iteration":650,"passed_time":0.8284381138,"remaining_time":0.444124273},
{"learn":[0.1735731279],"iteration":651,"passed_time":0.8294815309,"remaining_time":0.4427294061},
{"learn":[0.1728648844],"iteration":652,"passed_time":0.8304810087,"remaining_time":0.4413122665},
{"learn":[0.172158485],"iteration":653,"passed_time":0.8316255979,"remaining_time":0.4399731756},
{"learn":[0.1714361825],"iteration":654,"passed_time":0.832737776,"remaining_time":0.4386176072},
{"learn":[0.1712013425],"iteration":655,"passed_time":0.8338084483,"remaining_time":0.4372410156},
{"learn":[0.170969348],"iteration":656,"passed_time":0.8349866443,"remaining_time":0.4359214901},
{"learn":[0.1707401614],"iteration":657,"passed_time":0.8360881785,"remaining_time":0.4345625487},
{"learn":[0.170026649],"iteration":658,"passed_time":0.8373510654,"remaining_time":0.4332878806},
{"learn":[0.1697996199],"iteration":659,"passed_time":0.8385267564,"remaining_time":0.4319683291},
{"learn":[0.1695750916],"iteration":660,"passed_time":0.8398085368,"remaining_time":0.4307036217},
{"learn":[0.1693531586],"iteration":661,"passed_time":0.8409228429,"remaining_time":0.4293533548},
{"learn":[0.1686485962],"iteration":662,"passed_time":0.8421541047,"remaining_time":0.4280632478},
{"learn":[0.1674559278],"iteration":663,"passed_time":0.8434647498,"remaining_time":0.4268134879},
{"learn":[0.1667732473],"iteration":664,"passed_time":0.8445342036,"remaining_time":0.4254420424},
{"learn":[0.1665559552],"iteration":665,"passed_time":0.8456332509,"remaining_time":0.424086345},
{"learn":[0.1656437213],"iteration":666,"passed_time":0.8466657999,"remaining_time":0.4226982179},
{"learn":[0.1642194796],"iteration":667,"passed_time":0.8477467638,"remaining_time":0.421335218},
{"learn":[0.1628129169],"iteration":668,"passed_time":0.8487855373,"remaining_time":0.4199521866},
{"learn":[0.1614238384],"iteration":669,"passed_time":0.8499131245,"remaining_time":0.418613927},
{"learn":[0.1600520513],"iteration":670,"passed_time":0.8512049461,"remaining_time":0.4173568216},
{"learn":[0.158697365],"iteration":671,"passed_time":0.8526037055,"remaining_time":0.4161518086},
{"learn":[0.1573595911],"iteration":672,"passed_time":0.853793471,"remaining_time":0.4148446731},
{"learn":[0.1560385431],"iteration":673,"passed_time":0.8552475586,"remaining_time":0.4136657331},
{"learn":[0.1547340366],"iteration":674,"passed_time":0.8562623537,"remaining_time":0.4122744666},
{"learn":[0.1534458894],"iteration":675,"passed_time":0.8573836822,"remaining_time":0.4109353743},
{"learn":[0.1521739212],"iteration":676,"passed_time":0.8584714249,"remaining_time":0.4095809014},
{"learn":[0.1509179535],"iteration":677,"passed_time":0.8595205589,"remaining_time":0.408208879},
{"learn":[0.1496778099],"iteration":678,"passed_time":0.8606449422,"remaining_time":0.4068733821},
{"learn":[0.1484533159],"iteration":679,"passed_time":0.8617489155,"remaining_time":0.4055289014},
{"learn":[0.1472442989],"iteration":680,"passed_time":0.8627175402,"remaining_time":0.4041217259},
{"learn":[0.1460505882],"iteration":681,"passed_time":0.863811855,"remaining_time":0.4027744426},
{"learn":[0.1449611062],"iteration":682,"passed_time":0.8648975486,"remaining_time":0.4014238989},
{"learn":[0.1438857651],"iteration":683,"passed_time":0.8659066008,"remaining_time":0.400038722},
{"learn":[0.1428243932],"iteration":684,"passed_time":0.8671751421,"remaining_time":0.3987739705},
{"learn":[0.1417768208],"iteration":685,"passed_time":0.8683958256,"remaining_time":0.3974873021},
{"learn":[0.1407428803],"iteration":686,"passed_time":0.8694930095,"remaining_time":0.3961445589},
{"learn":[0.139722406],"iteration":687,"passed_time":0.8704914987,"remaining_time":0.3947577727},
{"learn":[0.1391548833],"iteration":688,"passed_time":0.8716335734,"remaining_time":0.393436925},
{"learn":[0.1381502283],"iteration":689,"passed_time":0.8725856749,"remaining_time":0.3920312452},
{"learn":[0.1371586781],"iteration":690,"passed_time":0.8735058911,"remaining_time":0.3906126199},
{"learn":[0.136603309],"iteration":691,"passed_time":0.8744779382,"remaining_time":0.3892185043},
{"learn":[0.1356271548],"iteration":692,"passed_time":0.8755940505,"remaining_time":0.3878894279},
{"learn":[0.1350812317],"iteration":693,"passed_time":0.8766663874,"remaining_time":0.3865416636},
{"learn":[0.1341202389],"iteration":694,"passed_time":0.8776688482,"remaining_time":0.3851640269},
{"learn":[0.1335835881],"iteration":695,"passed_time":0.8787321539,"remaining_time":0.3838140442},
{"learn":[0.1326375259],"iteration":696,"passed_time":0.8797892512,"remaining_time":0.3824621852},
{"learn":[0.1321099774],"iteration":697,"passed_time":0.8808428109,"remaining_time":0.3811096402},
{"learn":[0.1311786187],"iteration":698,"passed_time":0.8821967768,"remaining_time":0.3798873102},
{"learn":[0.1303145581],"iteration":699,"passed_time":0.8836286685,"remaining_time":0.3786980008},
{"learn":[0.1297998219],"iteration":700,"passed_time":0.8847417264,"remaining_time":0.377372006},
{"learn":[0.1288898466],"iteration":701,"passed_time":0.8859117797,"remaining_time":0.3760708125},
{"learn":[0.1283838174],"iteration":702,"passed_time":0.8871558795,"remaining_time":0.3748012748},
{"learn":[0.1275453182],"iteration":703,"passed_time":0.8882932498,"remaining_time":0.3734869346},
{"learn":[0.1267176215],"iteration":704,"passed_time":0.8894057382,"remaining_time":0.3721626848},
{"learn":[0.126225402],"iteration":705,"passed_time":0.890581039,"remaining_time":0.3708651919},
{"learn":[0.1252221291],"iteration":706,"passed_time":0.8918143317,"remaining_time":0.3695920781},
{"learn":[0.1244349534],"iteration":707,"passed_time":0.8930091835,"remaining_time":0.3683032226},
{"learn":[0.1236611388],"iteration":708,"passed_time":0.8941931985,"remaining_time":0.3670101844},
{"learn":[0.1229643085],"iteration":709,"passed_time":0.8952976544,"remaining_time":0.3656849574},
{"learn":[0.1223800028],"iteration":710,"passed_time":0.8963978859,"remaining_time":0.3643586343},
{"learn":[0.1216595415],"iteration":711,"passed_time":0.8979079487,"remaining_time":0.3631987208},
{"learn":[0.121087877],"iteration":712,"passed_time":0.8990641837,"remaining_time":0.3618954007},
{"learn":[0.1204191812],"iteration":713,"passed_time":0.9001086587,"remaining_time":0.360547726},
{"learn":[0.1197565749],"iteration":714,"passed_time":0.9012098324,"remaining_time":0.3592234996},
{"learn":[0.1192011618],"iteration":715,"passed_time":0.902306765,"remaining_time":0.3578982141},
{"learn":[0.1182181578],"iteration":716,"passed_time":0.9034496375,"remaining_time":0.3565916979},
{"learn":[0.1172516903],"iteration":717,"passed_time":0.9045684644,"remaining_time":0.3552761936},
{"learn":[0.1163015062],"iteration":718,"passed_time":0.9056674532,"remaining_time":0.3539534831},
{"learn":[0.1153673556],"iteration":719,"passed_time":0.9066784151,"remaining_time":0.3525971614},
{"learn":[0.114448992],"iteration":720,"passed_time":0.9076895091,"remaining_time":0.3512418489},
{"learn":[0.1140291611],"iteration":721,"passed_time":0.9087700134,"remaining_time":0.3499142157},
{"learn":[0.1136157922],"iteration":722,"passed_time":0.9098194754,"remaining_time":0.348575373},
{"learn":[0.1132087886],"iteration":723,"passed_time":0.9110075157,"remaining_time":0.3472901579},
{"learn":[0.1128080547],"iteration":724,"passed_time":0.9123484117,"remaining_time":0.3460631907},
{"learn":[0.1124134964],"iteration":725,"passed_time":0.9134556307,"remaining_time":0.3447477174},
{"learn":[0.1121532025],"iteration":726,"passed_time":0.9145979143,"remaining_time":0.3434459843},
{"learn":[0.1118575076],"iteration":727,"passed_time":0.9156984966,"remaining_time":0.3421291086},
{"learn":[0.1115679524],"iteration":728,"passed_time":0.9168185082,"remaining_time":0.340820049},
{"learn":[0.1112843843],"iteration":729,"passed_time":0.9178349779,"remaining_time":0.339473211},
{"learn":[0.1110066547],"iteration":730,"passed_time":0.9187612126,"remaining_time":0.3380940714},
{"learn":[0.1107346192],"iteration":731,"passed_time":0.9198264456,"remaining_time":0.3367670593},
{"learn":[0.1100929451],"iteration":732,"passed_time":0.9210126956,"remaining_time":0.3354848427},
{"learn":[0.1097167348],"iteration":733,"passed_time":0.9220956061,"remaining_time":0.3341654376},
{"learn":[0.1094535113],"iteration":734,"passed_time":0.9231619926,"remaining_time":0.3328407184},
{"learn":[0.1091956519],"iteration":735,"passed_time":0.9242806044,"remaining_time":0.3315354342},
{"learn":[0.1089430243],"iteration":736,"passed_time":0.9253854453,"remaining_time":0.3302257423},
{"learn":[0.1087168553],"iteration":737,"passed_time":0.9268230239,"remaining_time":0.329034732},
{"learn":[0.1080920601],"iteration":738,"passed_time":0.9281714399,"remaining_time":0.327811564},
{"learn":[0.1078716792],"iteration":739,"passed_time":0.9291203246,"remaining_time":0.3264476816},
{"learn":[0.1075928298],"iteration":740,"passed_time":0.930182551,"remaining_time":0.3251245354},
{"learn":[0.1069618894],"iteration":741,"passed_time":0.9311876179,"remaining_time":0.3237822176},
{"learn":[0.1066049264],"iteration":742,"passed_time":0.9322335645,"remaining_time":0.3224549476},
{"learn":[0.1059882953],"iteration":743,"passed_time":0.9333050494,"remaining_time":0.3211372213},
{"learn":[0.1056384971],"iteration":744,"passed_time":0.9344095163,"remaining_time":0.3198314452},
{"learn":[0.1052942144],"iteration":745,"passed_time":0.9356461156,"remaining_time":0.3185711975},
{"learn":[0.1046930481],"iteration":746,"passed_time":0.93678664,"remaining_time":0.3172784738},
{"learn":[0.1039783125],"iteration":747,"passed_time":0.9378362541,"remaining_time":0.3159555294},
{"learn":[0.1032725016],"iteration":748,"passed_time":0.9390483208,"remaining_time":0.314687755},
{"learn":[0.1025712181],"iteration":749,"passed_time":0.9400931727,"remaining_time":0.3133643909},
{"learn":[0.1018810286],"iteration":750,"passed_time":0.9414565463,"remaining_time":0.3121473769},
{"learn":[0.1011952957],"iteration":751,"passed_time":0.942570987,"remaining_time":0.3108478787},
{"learn":[0.1005204183],"iteration":752,"passed_time":0.9435867639,"remaining_time":0.3095165082},
{"learn":[0.09990950371],"iteration":753,"passed_time":0.944569193,"remaining_time":0.3081750948},
{"learn":[0.09958287139],"iteration":754,"passed_time":0.9454292482,"remaining_time":0.3067949216},
{"learn":[0.09926137262],"iteration":755,"passed_time":0.9464236347,"remaining_time":0.30545948},
{"learn":[0.09894492802],"iteration":756,"passed_time":0.9474751454,"remaining_time":0.3041432765},
{"learn":[0.0986334593],"iteration":757,"passed_time":0.9486887736,"remaining_time":0.3028795293},
{"learn":[0.09832688928],"iteration":758,"passed_time":0.9496994993,"remaining_time":0.3015514879},
{"learn":[0.09767087364],"iteration":759,"passed_time":0.950770057,"remaining_time":0.3002431759},
{"learn":[0.0970446055],"iteration":760,"passed_time":0.9517758191,"remaining_time":0.298915139},
{"learn":[0.09640310056],"iteration":761,"passed_time":0.9528752783,"remaining_time":0.2976172129},
{"learn":[0.09579065109],"iteration":762,"passed_time":0.9539705645,"remaining_time":0.2963185109},
{"learn":[0.09516337203],"iteration":763,"passed_time":0.9550593558,"remaining_time":0.295018335},
{"learn":[0.09456446815],"iteration":764,"passed_time":0.9565869327,"remaining_time":0.2938535022},
{"learn":[0.09394355022],"iteration":765,"passed_time":0.9576762207,"remaining_time":0.2925538324},
{"learn":[0.09374448092],"iteration":766,"passed_time":0.9587575466,"remaining_time":0.2912522925},
{"learn":[0.09313827904],"iteration":767,"passed_time":0.959867729,"remaining_time":0.2899600431},
{"learn":[0.09255946457],"iteration":768,"passed_time":0.960905234,"remaining_time":0.2886464357},
{"learn":[0.09198774789],"iteration":769,"passed_time":0.9618252325,"remaining_time":0.2872984461},
{"learn":[0.09140084217],"iteration":770,"passed_time":0.9628534572,"remaining_time":0.2859837117},
{"learn":[0.09091854317],"iteration":771,"passed_time":0.9640006379,"remaining_time":0.2847048516},
{"learn":[0.09023425686],"iteration":772,"passed_time":0.9650756725,"remaining_time":0.2834051458},
{"learn":[0.08995093942],"iteration":773,"passed_time":0.9662094253,"remaining_time":0.2821231655},
{"learn":[0.08975317552],"iteration":774,"passed_time":0.967278287,"remaining_time":0.2808227285},
{"learn":[0.08955801915],"iteration":775,"passed_time":0.9683252218,"remaining_time":0.2795165589},
{"learn":[0.08937226141],"iteration":776,"passed_time":0.9695256552,"remaining_time":0.2782551108},
{"learn":[0.08915776758],"iteration":777,"passed_time":0.971020061,"remaining_time":0.2770777038},
{"learn":[0.08865377097],"iteration":778,"passed_time":0.9720273368,"remaining_time":0.2757612855},
{"learn":[0.08838255968],"iteration":779,"passed_time":0.973094118,"remaining_time":0.2744624435},
{"learn":[0.08817433771],"iteration":780,"passed_time":0.9742005033,"remaining_time":0.2731753012},
{"learn":[0.08797032002],"iteration":781,"passed_time":0.9752916469,"remaining_time":0.2718843721},
{"learn":[0.08742585963],"iteration":782,"passed_time":0.9763104554,"remaining_time":0.2705739065},
{"learn":[0.08674957921],"iteration":783,"passed_time":0.9774450555,"remaining_time":0.2692960867},
{"learn":[0.08655003338],"iteration":784,"passed_time":0.9785279988,"remaining_time":0.2680044838},
{"learn":[0.08606745001],"iteration":785,"passed_time":0.9795859142,"remaining_time":0.2667065975},
{"learn":[0.08559471019],"iteration":786,"passed_time":0.9807818891,"remaining_time":0.2654466866},
{"learn":[0.08533593603],"iteration":787,"passed_time":0.9819903533,"remaining_time":0.2641902981},
{"learn":[0.08472158944],"iteration":788,"passed_time":0.9831021678,"remaining_time":0.2629081843},
{"learn":[0.08411523166],"iteration":789,"passed_time":0.9841923785,"remaining_time":0.2616207588},
{"learn":[0.08351677967],"iteration":790,"passed_time":0.9856409122,"remaining_time":0.260428509},
{"learn":[0.08292615121],"iteration":791,"passed_time":0.9868156581,"remaining_time":0.2591637082},
{"learn":[0.08223937138],"iteration":792,"passed_time":0.98785248,"remaining_time":0.2578631316},
{"learn":[0.08171430321],"iteration":793,"passed_time":0.9889378642,"remaining_time":0.2565758187},
{"learn":[0.08109220599],"iteration":794,"passed_time":0.9899166829,"remaining_time":0.2552615346},
{"learn":[0.0804788941],"iteration":795,"passed_time":0.9909206227,"remaining_time":0.2539545314},
{"learn":[0.080288437],"iteration":796,"passed_time":0.9919552435,"remaining_time":0.2526561034},
{"learn":[0.08010180986],"iteration":797,"passed_time":0.9930132107,"remaining_time":0.2513642463},
{"learn":[0.07949798707],"iteration":798,"passed_time":0.9941228156,"remaining_time":0.2500859649},
{"learn":[0.07931549539],"iteration":799,"passed_time":0.9954104053,"remaining_time":0.2488526013},
{"learn":[0.07913663875],"iteration":800,"passed_time":0.9965149247,"remaining_time":0.2475736205},
{"learn":[0.07854212813],"iteration":801,"passed_time":0.9978195413,"remaining_time":0.2463444753},
{"learn":[0.0783671987],"iteration":802,"passed_time":0.9987919956,"remaining_time":0.2450336527},
{"learn":[0.07821253811],"iteration":803,"passed_time":1.000120476,"remaining_time":0.2438104644},
{"learn":[0.07762717366],"iteration":804,"passed_time":1.00135061,"remaining_time":0.2425631912},
{"learn":[0.07752166053],"iteration":805,"passed_time":1.002368079,"remaining_time":0.2412647735},
{"learn":[0.07741743727],"iteration":806,"passed_time":1.003591116,"remaining_time":0.2400162148},
{"learn":[0.07684045571],"iteration":807,"passed_time":1.004849746,"remaining_time":0.2387761772},
{"learn":[0.07673755544],"iteration":808,"passed_time":1.006103991,"remaining_time":0.2375350583},
{"learn":[0.076602644],"iteration":809,"passed_time":1.007245362,"remaining_time":0.2362674306},
{"learn":[0.07646975379],"iteration":810,"passed_time":1.008330535,"remaining_time":0.2349870174},
{"learn":[0.07633884713],"iteration":811,"passed_time":1.009403236,"remaining_time":0.2337041976},
{"learn":[0.07620988732],"iteration":812,"passed_time":1.010474433,"remaining_time":0.2324215484},
{"learn":[0.07611209972],"iteration":813,"passed_time":1.011898455,"remaining_time":0.23122004},
{"learn":[0.07554549616],"iteration":814,"passed_time":1.013055929,"remaining_time":0.2299574807},
{"learn":[0.0754488944],"iteration":815,"passed_time":1.014147887,"remaining_time":0.228680406},
{"learn":[0.07535344476],"iteration":816,"passed_time":1.015574985,"remaining_time":0.2274788523},
{"learn":[0.07525913322],"iteration":817,"passed_time":1.017141299,"remaining_time":0.2263077219},
{"learn":[0.0747005526],"iteration":818,"passed_time":1.018313937,"remaining_time":0.2250486235},
{"learn":[0.07460736956],"iteration":819,"passed_time":1.019509312,"remaining_time":0.223794727},
{"learn":[0.07451529415],"iteration":820,"passed_time":1.020623419,"remaining_time":0.2225232545},
{"learn":[0.07396459537],"iteration":821,"passed_time":1.021717939,"remaining_time":0.2212479236},
{"learn":[0.07387360987],"iteration":822,"passed_time":1.022752832,"remaining_time":0.219960208},
{"learn":[0.073783703],"iteration":823,"passed_time":1.023817086,"remaining_time":0.2186793776},
{"learn":[0.07324076423],"iteration":824,"passed_time":1.02483309,"remaining_time":0.2173888372},
{"learn":[0.07315191087],"iteration":825,"passed_time":1.026014772,"remaining_time":0.2161338623},
{"learn":[0.07261663084],"iteration":826,"passed_time":1.027108048,"remaining_time":0.2148605712},
{"learn":[0.07252880992],"iteration":827,"passed_time":1.028230729,"remaining_time":0.2135938229},
{"learn":[0.07244202565],"iteration":828,"passed_time":1.02930765,"remaining_time":0.2123179833},
{"learn":[0.07191427699],"iteration":829,"passed_time":1.031093226,"remaining_time":0.2111877692},
{"learn":[0.07183153302],"iteration":830,"passed_time":1.032366529,"remaining_time":0.2099517971},
{"learn":[0.07131115462],"iteration":831,"passed_time":1.033476133,"remaining_time":0.2086826807},
{"learn":[0.07122934403],"iteration":832,"passed_time":1.034477191,"remaining_time":0.2073921859},
{"learn":[0.07114856078],"iteration":833,"passed_time":1.035413462,"remaining_time":0.2060894901},
{"learn":[0.07063534663],"iteration":834,"passed_time":1.036361391,"remaining_time":0.2047899754},
{"learn":[0.07055546864],"iteration":835,"passed_time":1.037429102,"remaining_time":0.2035147999},
{"learn":[0.07004943051],"iteration":836,"passed_time":1.038535107,"remaining_time":0.2022475777},
{"learn":[0.0699704428],"iteration":837,"passed_time":1.03957883,"remaining_time":0.2009686999},
{"learn":[0.0694714867],"iteration":838,"passed_time":1.04084742,"remaining_time":0.1997335336},
{"learn":[0.06939337477],"iteration":839,"passed_time":1.041942535,"remaining_time":0.1984652448},
{"learn":[0.06891528936],"iteration":840,"passed_time":1.043092288,"remaining_time":0.1972076978},
{"learn":[0.06883360822],"iteration":841,"passed_time":1.044198565,"remaining_time":0.1959422485},
{"learn":[0.06875300577],"iteration":842,"passed_time":1.045357913,"remaining_time":0.194687061},
{"learn":[0.06826746943],"iteration":843,"passed_time":1.046741978,"remaining_time":0.1934736357},
{"learn":[0.06818792928],"iteration":844,"passed_time":1.047954762,"remaining_time":0.1922283883},
{"learn":[0.06810942787],"iteration":845,"passed_time":1.048968925,"remaining_time":0.1909470619},
{"learn":[0.06803194865],"iteration":846,"passed_time":1.050105094,"remaining_time":0.1896884054},
{"learn":[0.06760950099],"iteration":847,"passed_time":1.051071899,"remaining_time":0.1883996799},
{"learn":[0.06753334252],"iteration":848,"passed_time":1.052129481,"remaining_time":0.1871278583},
{"learn":[0.0673359035],"iteration":849,"passed_time":1.053355638,"remaining_time":0.1858862891},
{"learn":[0.06691047609],"iteration":850,"passed_time":1.054523793,"remaining_time":0.1846346006},
{"learn":[0.06683571984],"iteration":851,"passed_time":1.055749827,"remaining_time":0.1833931624},
{"learn":[0.06676193272],"iteration":852,"passed_time":1.056800059,"remaining_time":0.1821214639},
{"learn":[0.0663556687],"iteration":853,"passed_time":1.05798415,"remaining_time":0.1808731686},
{"learn":[0.06628300433],"iteration":854,"passed_time":1.059408631,"remaining_time":0.1796657912},
{"learn":[0.06587223789],"iteration":855,"passed_time":1.06097107,"remaining_time":0.1784811146},
{"learn":[0.06580062535],"iteration":856,"passed_time":1.062175548,"remaining_time":0.1772358265},
{"learn":[0.06561061939],"iteration":857,"passed_time":1.063160146,"remaining_time":0.1759542432},
{"learn":[0.06520800444],"iteration":858,"passed_time":1.064174113,"remaining_time":0.1746781722},
{"learn":[0.06510846731],"iteration":859,"passed_time":1.065152639,"remaining_time":0.1733969412},
{"learn":[0.06503868127],"iteration":860,"passed_time":1.066092363,"remaining_time":0.1721101492},
{"learn":[0.06469181072],"iteration":861,"passed_time":1.067319972,"remaining_time":0.1708702507},
{"learn":[0.06435087315],"iteration":862,"passed_time":1.068496264,"remaining_time":0.1696222343},
{"learn":[0.06401576524],"iteration":863,"passed_time":1.069540034,"remaining_time":0.1683535238},
{"learn":[0.06368638538],"iteration":864,"passed_time":1.070580175,"remaining_time":0.1670847672},
{"learn":[0.06336263371],"iteration":865,"passed_time":1.071705745,"remaining_time":0.1658297573},
{"learn":[0.06304441204],"iteration":866,"passed_time":1.072758661,"remaining_time":0.1645639006},
{"learn":[0.0625489004],"iteration":867,"passed_time":1.073856803,"remaining_time":0.1633054124},
{"learn":[0.06206176921],"iteration":868,"passed_time":1.075195125,"remaining_time":0.1620834998},
{"learn":[0.06188615375],"iteration":869,"passed_time":1.076287839,"remaining_time":0.1608246197},
{"learn":[0.06140876543],"iteration":870,"passed_time":1.07728149,"remaining_time":0.1595514491},
{"learn":[0.06123749407],"iteration":871,"passed_time":1.078318395,"remaining_time":0.158285269},
{"learn":[0.06115884898],"iteration":872,"passed_time":1.079310483,"remaining_time":0.1570130943},
{"learn":[0.06099094075],"iteration":873,"passed_time":1.080271704,"remaining_time":0.1557371106},
{"learn":[0.06092400306],"iteration":874,"passed_time":1.081291228,"remaining_time":0.1544701755},
{"learn":[0.0604306649],"iteration":875,"passed_time":1.08247252,"remaining_time":0.1532267037},
{"learn":[0.06036519776],"iteration":876,"passed_time":1.08360317,"remaining_time":0.1519762713},
{"learn":[0.06029062276],"iteration":877,"passed_time":1.084732917,"remaining_time":0.1507259861},
{"learn":[0.06022738372],"iteration":878,"passed_time":1.085933287,"remaining_time":0.1494856971},
{"learn":[0.06004466139],"iteration":879,"passed_time":1.087016203,"remaining_time":0.1482294822},
{"learn":[0.0595635454],"iteration":880,"passed_time":1.088137556,"remaining_time":0.1469788527},
{"learn":[0.05910792107],"iteration":881,"passed_time":1.089510571,"remaining_time":0.1457621853},
{"learn":[0.05904624136],"iteration":882,"passed_time":1.091292084,"remaining_time":0.1445992909},
{"learn":[0.0589852828],"iteration":883,"passed_time":1.092455399,"remaining_time":0.1433538758},
{"learn":[0.0589145799],"iteration":884,"passed_time":1.09361882,"remaining_time":0.1421086602},
{"learn":[0.05855965469],"iteration":885,"passed_time":1.094703308,"remaining_time":0.1408534731},
{"learn":[0.05809620215],"iteration":886,"passed_time":1.095875535,"remaining_time":0.1396098483},
{"learn":[0.05792175875],"iteration":887,"passed_time":1.097073879,"remaining_time":0.1383696784},
{"learn":[0.05754875949],"iteration":888,"passed_time":1.098172426,"remaining_time":0.137117142},
{"learn":[0.05720440671],"iteration":889,"passed_time":1.099289023,"remaining_time":0.1358671826},
{"learn":[0.0568394503],"iteration":890,"passed_time":1.100424627,"remaining_time":0.1346198478},
{"learn":[0.0564428306],"iteration":891,"passed_time":1.10157795,"remaining_time":0.1333749088},
{"learn":[0.05638498879],"iteration":892,"passed_time":1.102725226,"remaining_time":0.1321294504},
{"learn":[0.05632782406],"iteration":893,"passed_time":1.104286469,"remaining_time":0.130933295},
{"learn":[0.05599279109],"iteration":894,"passed_time":1.106076552,"remaining_time":0.1297631709},
{"learn":[0.05563991362],"iteration":895,"passed_time":1.107168998,"remaining_time":0.1285106872},
{"learn":[0.05525544891],"iteration":896,"passed_time":1.108174765,"remaining_time":0.1272486073},
{"learn":[0.0551995201],"iteration":897,"passed_time":1.109161573,"remaining_time":0.1259849449},
{"learn":[0.05503601786],"iteration":898,"passed_time":1.110281663,"remaining_time":0.124736872},
{"learn":[0.0546763529],"iteration":899,"passed_time":1.111605811,"remaining_time":0.1235117568},
{"learn":[0.05430160362],"iteration":900,"passed_time":1.112901435,"remaining_time":0.1222832875},
{"learn":[0.05411714284],"iteration":901,"passed_time":1.113911543,"remaining_time":0.1210236488},
{"learn":[0.05406283321],"iteration":902,"passed_time":1.114945149,"remaining_time":0.1197670869},
{"learn":[0.05390420127],"iteration":903,"passed_time":1.116061299,"remaining_time":0.1185197839},
{"learn":[0.05341023623],"iteration":904,"passed_time":1.117337612,"remaining_time":0.1172895836},
{"learn":[0.05335683061],"iteration":905,"passed_time":1.118918733,"remaining_time":0.116090906},
{"learn":[0.05330404966],"iteration":906,"passed_time":1.120225608,"remaining_time":0.1148632652},
{"learn":[0.05315011304],"iteration":907,"passed_time":1.121265148,"remaining_time":0.113608363},
{"learn":[0.05278601594],"iteration":908,"passed_time":1.122296777,"remaining_time":0.1123531427},
{"learn":[0.05261012302],"iteration":909,"passed_time":1.123449408,"remaining_time":0.111110381},
{"learn":[0.05255605416],"iteration":910,"passed_time":1.124452691,"remaining_time":0.1098532266},
{"learn":[0.05221245248],"iteration":911,"passed_time":1.125674113,"remaining_time":0.1086176776},
{"learn":[0.05215915284],"iteration":912,"passed_time":1.128006463,"remaining_time":0.1074880201},
{"learn":[0.05201026676],"iteration":913,"passed_time":1.129131268,"remaining_time":0.1062421105},
{"learn":[0.0516562613],"iteration":914,"passed_time":1.130255349,"remaining_time":0.1049963986},
{"learn":[0.05152329148],"iteration":915,"passed_time":1.131508291,"remaining_time":0.1037627691},
{"learn":[0.05118774265],"iteration":916,"passed_time":1.132688698,"remaining_time":0.1025225321},
{"learn":[0.05105943412],"iteration":917,"passed_time":1.135801938,"remaining_time":0.1014550751},
{"learn":[0.05099481265],"iteration":918,"passed_time":1.1385828,"remaining_time":0.1003538703},
{"learn":[0.05065093267],"iteration":919,"passed_time":1.140461788,"remaining_time":0.09917059023},
{"learn":[0.05058756716],"iteration":920,"passed_time":1.14213649,"remaining_time":0.09796827658},
{"learn":[0.05052468885],"iteration":921,"passed_time":1.143466908,"remaining_time":0.09673581214},
{"learn":[0.05023342194],"iteration":922,"passed_time":1.145061009,"remaining_time":0.09552513289},
{"learn":[0.05011190774],"iteration":923,"passed_time":1.146617771,"remaining_time":0.0943105526},
{"learn":[0.04978750156],"iteration":924,"passed_time":1.149264322,"remaining_time":0.09318359371},
{"learn":[0.04945380171],"iteration":925,"passed_time":1.152349057,"remaining_time":0.09208836959},
{"learn":[0.04939360214],"iteration":926,"passed_time":1.154046127,"remaining_time":0.09087957636},
{"learn":[0.04933319915],"iteration":927,"passed_time":1.15591609,"remaining_time":0.08968314494},
{"learn":[0.04900517973],"iteration":928,"passed_time":1.157212956,"remaining_time":0.08844146384},
{"learn":[0.04894651247],"iteration":929,"passed_time":1.158510599,"remaining_time":0.08719972249},
{"learn":[0.04888733373],"iteration":930,"passed_time":1.160090302,"remaining_time":0.0859787657},
{"learn":[0.04874953941],"iteration":931,"passed_time":1.161446804,"remaining_time":0.08474075391},
{"learn":[0.04843526957],"iteration":932,"passed_time":1.163028927,"remaining_time":0.08351869034},
{"learn":[0.048115132],"iteration":933,"passed_time":1.165215616,"remaining_time":0.08233857669},
{"learn":[0.04805852501],"iteration":934,"passed_time":1.166970487,"remaining_time":0.08112629057},
{"learn":[0.04792447222],"iteration":935,"passed_time":1.168466322,"remaining_time":0.07989513315},
{"learn":[0.04761021213],"iteration":936,"passed_time":1.169713599,"remaining_time":0.07864669875},
{"learn":[0.04752025739],"iteration":937,"passed_time":1.171763531,"remaining_time":0.07745132078},
{"learn":[0.04746519086],"iteration":938,"passed_time":1.17311448,"remaining_time":0.07620871486},
{"learn":[0.04726064683],"iteration":939,"passed_time":1.174525903,"remaining_time":0.07496973851},
{"learn":[0.04695331849],"iteration":940,"passed_time":1.175929652,"remaining_time":0.07372991439},
{"learn":[0.04691133963],"iteration":941,"passed_time":1.178123945,"remaining_time":0.07253841703},
{"learn":[0.04678267273],"iteration":942,"passed_time":1.180655054,"remaining_time":0.0713651517},
{"learn":[0.04648229772],"iteration":943,"passed_time":1.18276101,"remaining_time":0.07016378874},
{"learn":[0.04618211819],"iteration":944,"passed_time":1.184234679,"remaining_time":0.06892371148},
{"learn":[0.04612985996],"iteration":945,"passed_time":1.186186695,"remaining_time":0.06771044562},
{"learn":[0.04583483143],"iteration":946,"passed_time":1.188949604,"remaining_time":0.06654100214},
{"learn":[0.04575045691],"iteration":947,"passed_time":1.192264406,"remaining_time":0.0653984695},
{"learn":[0.04562969771],"iteration":948,"passed_time":1.193626604,"remaining_time":0.06414642446},
{"learn":[0.04533817983],"iteration":949,"passed_time":1.198303806,"remaining_time":0.06306862137},
{"learn":[0.04499784978],"iteration":950,"passed_time":1.201391887,"remaining_time":0.06190136959},
{"learn":[0.04471350642],"iteration":951,"passed_time":1.203095145,"remaining_time":0.06066025939},
{"learn":[0.04467434627],"iteration":952,"passed_time":1.205048357,"remaining_time":0.05943050661},
{"learn":[0.04462500103],"iteration":953,"passed_time":1.207064575,"remaining_time":0.05820227511},
{"learn":[0.04450464355],"iteration":954,"passed_time":1.208590575,"remaining_time":0.0569492941},
{"learn":[0.04432338279],"iteration":955,"passed_time":1.210297789,"remaining_time":0.05570408236},
{"learn":[0.04399264134],"iteration":956,"passed_time":1.212150987,"remaining_time":0.05446446439},
{"learn":[0.0437182006],"iteration":957,"passed_time":1.213774622,"remaining_time":0.05321350116},
{"learn":[0.04367078336],"iteration":958,"passed_time":1.215157223,"remaining_time":0.05195145583},
{"learn":[0.04347854616],"iteration":959,"passed_time":1.216376137,"remaining_time":0.05068233905},
{"learn":[0.04343230667],"iteration":960,"passed_time":1.217596465,"remaining_time":0.04941338412},
{"learn":[0.04325740101],"iteration":961,"passed_time":1.218824189,"remaining_time":0.04814482243},
{"learn":[0.0430705218],"iteration":962,"passed_time":1.220062852,"remaining_time":0.04687676586},
{"learn":[0.04288786588],"iteration":963,"passed_time":1.221710456,"remaining_time":0.04562404192},
{"learn":[0.04264066625],"iteration":964,"passed_time":1.222941887,"remaining_time":0.04435540523},
{"learn":[0.04250237155],"iteration":965,"passed_time":1.224052537,"remaining_time":0.04308259448},
{"learn":[0.04219067744],"iteration":966,"passed_time":1.225874886,"remaining_time":0.04183440666},
{"learn":[0.04193141323],"iteration":967,"passed_time":1.227402201,"remaining_time":0.04057527936},
{"learn":[0.04179713187],"iteration":968,"passed_time":1.229310346,"remaining_time":0.03932778198},
{"learn":[0.04153986112],"iteration":969,"passed_time":1.230519919,"remaining_time":0.03805731707},
{"learn":[0.04130042561],"iteration":970,"passed_time":1.231696802,"remaining_time":0.03678600129},
{"learn":[0.04122590175],"iteration":971,"passed_time":1.232795009,"remaining_time":0.03551261343},
{"learn":[0.04099218197],"iteration":972,"passed_time":1.234039113,"remaining_time":0.03424363417},
{"learn":[0.0407586909],"iteration":973,"passed_time":1.235111238,"remaining_time":0.03297011518},
{"learn":[0.04050867488],"iteration":974,"passed_time":1.236448278,"remaining_time":0.031703802},
{"learn":[0.04023414803],"iteration":975,"passed_time":1.237777315,"remaining_time":0.03043714709},
{"learn":[0.04010697153],"iteration":976,"passed_time":1.238946051,"remaining_time":0.02916659077},
{"learn":[0.0398641956],"iteration":977,"passed_time":1.240424886,"remaining_time":0.0279032183},
{"learn":[0.03959755],"iteration":978,"passed_time":1.242019975,"remaining_time":0.02664189936},
{"learn":[0.03947473341],"iteration":979,"passed_time":1.24327954,"remaining_time":0.02537305183},
{"learn":[0.03935409736],"iteration":980,"passed_time":1.244800374,"remaining_time":0.0241092835},
{"learn":[0.03931320633],"iteration":981,"passed_time":1.245822216,"remaining_time":0.0228358451},
{"learn":[0.03906440252],"iteration":982,"passed_time":1.246992848,"remaining_time":0.02156549177},
{"learn":[0.03877482074],"iteration":983,"passed_time":1.248380641,"remaining_time":0.02029887221},
{"learn":[0.03870435206],"iteration":984,"passed_time":1.249595578,"remaining_time":0.01902937428},
{"learn":[0.03863581565],"iteration":985,"passed_time":1.250701372,"remaining_time":0.01775843733},
{"learn":[0.03841715321],"iteration":986,"passed_time":1.252060649,"remaining_time":0.01649117369},
{"learn":[0.03818664033],"iteration":987,"passed_time":1.253182492,"remaining_time":0.01522083999},
{"learn":[0.03805128314],"iteration":988,"passed_time":1.254627031,"remaining_time":0.01395439569},
{"learn":[0.03791871188],"iteration":989,"passed_time":1.258889002,"remaining_time":0.01271605053},
{"learn":[0.0376907041],"iteration":990,"passed_time":1.260332508,"remaining_time":0.01144600663},
{"learn":[0.03744055454],"iteration":991,"passed_time":1.261558553,"remaining_time":0.0101738593},
{"learn":[0.03732777823],"iteration":992,"passed_time":1.263106076,"remaining_time":0.008904071029},
{"learn":[0.03709312484],"iteration":993,"passed_time":1.264248381,"remaining_time":0.007631277951},
{"learn":[0.03685030166],"iteration":994,"passed_time":1.265351675,"remaining_time":0.006358551129},
{"learn":[0.03657375423],"iteration":995,"passed_time":1.266992642,"remaining_time":0.005088323864},
{"learn":[0.03630422599],"iteration":996,"passed_time":1.268666984,"remaining_time":0.003817453313},
{"learn":[0.03602036423],"iteration":997,"passed_time":1.272178355,"remaining_time":0.002549455622},
{"learn":[0.03586699986],"iteration":998,"passed_time":1.273968859,"remaining_time":0.001275244103},
{"learn":[0.03560924937],"iteration":999,"passed_time":1.275242592,"remaining_time":0}
]}